{
    "Changes": [
    
        {
            "LogName": "Object Data Tokens - Ancient_Fruit Syrup",
            "Action": "Include",
            "FromFile": "Data/Templates/Objects.json, Data/Templates/{{Method}}.json",
            "LocalTokens": {
                "MACHINE_TYPE": "{{ModId}}_SyrupMaker",
                "ITEM_TYPE": "Syrup",
                "ITEM_FLAVOR":"Ancient_Fruit",
                "INPUT1":"id_(O)454",
                "INPUT1_COUNT":3,
                "INPUT2":"",
                "PRICE_MULTIPLIER": 3.25,
                "PRICE_ADDER": 0,
                "MINUTES_UNTIL_READY": 20,
                "OBJECT_TYPE":"ArtisanGoods",
                "OBJECT_CATEGORY":-26,
                "OBJECT_PRICE":2040,
                "EDIBILITY":0,
                "DRINKABILITY":false,
                "ITEM_SPRITE":81,
                 //hybrid tokens
                "RECIPE_ACQUISITION":"default",
                "RECIPE_YIELD": 1,
                "ING1":"454",
                "ING1_COUNT":"3",
                "ING2":"245",
                "ING2_COUNT": 1,
                "ING3":"",
                "ING3_COUNT":"",
                "ING4":"",
                "ING4_COUNT":"",
                "ING5":"",
                "ING5_COUNT":"",
            }
        },

        {
            "LogName": "Object Data Tokens - Apple Syrup",
            "Action": "Include",
            "FromFile": "Data/Templates/Objects.json, Data/Templates/{{Method}}.json",
            "LocalTokens": {
                "MACHINE_TYPE": "{{ModId}}_SyrupMaker",
                "ITEM_TYPE": "Syrup",
                "ITEM_FLAVOR":"Apple",
                "INPUT1":"id_(O)613",
                "INPUT1_COUNT":3,
                "INPUT2":"",
                "PRICE_MULTIPLIER": 3.25,
                "PRICE_ADDER": 0,
                "MINUTES_UNTIL_READY": 20,
                "OBJECT_TYPE":"ArtisanGoods",
                "OBJECT_CATEGORY":-26,
                "OBJECT_PRICE":420,
                "EDIBILITY":0,
                "DRINKABILITY":false,
                "ITEM_SPRITE":82,
                 //hybrid tokens
                "RECIPE_ACQUISITION":"default",
                "RECIPE_YIELD": 1,
                "ING1":"613",
                "ING1_COUNT":"3",
                "ING2":"245",
                "ING2_COUNT": 1,
                "ING3":"",
                "ING3_COUNT":"",
                "ING4":"",
                "ING4_COUNT":"",
                "ING5":"",
                "ING5_COUNT":"",
            }
        },

        {
            "LogName": "Object Data Tokens - Apricot Syrup",
            "Action": "Include",
            "FromFile": "Data/Templates/Objects.json, Data/Templates/{{Method}}.json",
            "LocalTokens": {
                "MACHINE_TYPE": "{{ModId}}_SyrupMaker",
                "ITEM_TYPE": "Syrup",
                "ITEM_FLAVOR":"Apricot",
                "INPUT1":"id_(O)634",
                "INPUT1_COUNT":3,
                "INPUT2":"",
                "PRICE_MULTIPLIER": 3.25,
                "PRICE_ADDER": 0,
                "MINUTES_UNTIL_READY": 20,
                "OBJECT_TYPE":"ArtisanGoods",
                "OBJECT_CATEGORY":-26,
                "OBJECT_PRICE":240,
                "EDIBILITY":0,
                "DRINKABILITY":false,
                "ITEM_SPRITE":83,
                 //hybrid tokens
                "RECIPE_ACQUISITION":"default",
                "RECIPE_YIELD": 1,
                "ING1":"634",
                "ING1_COUNT":"3",
                "ING2":"245",
                "ING2_COUNT": 1,
                "ING3":"",
                "ING3_COUNT":"",
                "ING4":"",
                "ING4_COUNT":"",
                "ING5":"",
                "ING5_COUNT":"",
            }
        },
        {
            "LogName": "Object Data Tokens - Banana Syrup",
            "Action": "Include",
            "FromFile": "Data/Templates/Objects.json, Data/Templates/{{Method}}.json",
            "LocalTokens": {
                "MACHINE_TYPE": "{{ModId}}_SyrupMaker",
                "ITEM_TYPE": "Syrup",
                "ITEM_FLAVOR":"Banana",
                "INPUT1":"id_(O)91",
                "INPUT1_COUNT":3,
                "INPUT2":"",
                "PRICE_MULTIPLIER": 3.25,
                "PRICE_ADDER": 0,
                "MINUTES_UNTIL_READY": 20,
                "OBJECT_TYPE":"ArtisanGoods",
                "OBJECT_CATEGORY":-26,
                "OBJECT_PRICE":600,
                "EDIBILITY":0,
                "DRINKABILITY":false,
                "ITEM_SPRITE":84,
                 //hybrid tokens
                "RECIPE_ACQUISITION":"default",
                "RECIPE_YIELD": 1,
                "ING1":"91",
                "ING1_COUNT":"3",
                "ING2":"245",
                "ING2_COUNT": 1,
                "ING3":"",
                "ING3_COUNT":"",
                "ING4":"",
                "ING4_COUNT":"",
                "ING5":"",
                "ING5_COUNT":"",
            }
        },
        {
            "LogName": "Object Data Tokens - Cherry Syrup",
            "Action": "Include",
            "FromFile": "Data/Templates/Objects.json, Data/Templates/{{Method}}.json",
            "LocalTokens": {
                "MACHINE_TYPE": "{{ModId}}_SyrupMaker",
                "ITEM_TYPE": "Syrup",
                "ITEM_FLAVOR":"Cherry",
                "INPUT1":"id_(O)638",
                "INPUT1_COUNT":3,
                "INPUT2":"",
                "PRICE_MULTIPLIER": 3.25,
                "PRICE_ADDER": 0,
                "MINUTES_UNTIL_READY": 20,
                "OBJECT_TYPE":"ArtisanGoods",
                "OBJECT_CATEGORY":-26,
                "OBJECT_PRICE":348,
                "EDIBILITY":0,
                "DRINKABILITY":false,
                "ITEM_SPRITE":85,
                 //hybrid tokens
                "RECIPE_ACQUISITION":"default",
                "RECIPE_YIELD": 1,
                "ING1":"638",
                "ING1_COUNT":"3",
                "ING2":"245",
                "ING2_COUNT": 1,
                "ING3":"",
                "ING3_COUNT":"",
                "ING4":"",
                "ING4_COUNT":"",
                "ING5":"",
                "ING5_COUNT":"",
            }
        },
         {
            "LogName": "Object Data Tokens - Gem Syrup",
            "Action": "Include",
            "FromFile": "Data/Templates/Objects.json, Data/Templates/{{Method}}.json",
            "LocalTokens": {
                "MACHINE_TYPE": "{{ModId}}_SyrupMaker",
                "ITEM_TYPE": "Syrup",
                "ITEM_FLAVOR":"Gem",
                "INPUT1":"id_(O)417",
                "INPUT1_COUNT":3,
                "INPUT2":"",
                "PRICE_MULTIPLIER": 3.25,
                "PRICE_ADDER": 0,
                "MINUTES_UNTIL_READY": 20,
                "OBJECT_TYPE":"ArtisanGoods",
                "OBJECT_CATEGORY":-26,
                "OBJECT_PRICE":10860,
                "EDIBILITY":0,
                "DRINKABILITY":false,
                "ITEM_SPRITE":93,
                 //hybrid tokens
                "RECIPE_ACQUISITION":"default",
                "RECIPE_YIELD": 1,
                "ING1":"417",
                "ING1_COUNT":"3",
                "ING2":"245",
                "ING2_COUNT": 1,
                "ING3":"",
                "ING3_COUNT":"",
                "ING4":"",
                "ING4_COUNT":"",
                "ING5":"",
                "ING5_COUNT":"",
            }
        },
        {
            "LogName": "Object Data Tokens - Grenadine Syrup",
            "Action": "Include",
            "FromFile": "Data/Templates/Objects.json, Data/Templates/{{Method}}.json",
            "LocalTokens": {
                "MACHINE_TYPE": "{{ModId}}_SyrupMaker",
                "ITEM_TYPE": "Syrup",
                "ITEM_FLAVOR":"Grenadine",
                "INPUT1":"id_(O)637",
                "INPUT1_COUNT":3,
                "INPUT2":"",
                "PRICE_MULTIPLIER": 3.25,
                "PRICE_ADDER": 0,
                "MINUTES_UNTIL_READY": 20,
                "OBJECT_TYPE":"ArtisanGoods",
                "OBJECT_CATEGORY":-26,
                "OBJECT_PRICE":564,
                "EDIBILITY":0,
                "DRINKABILITY":false,
                "ITEM_SPRITE":86,
                 //hybrid tokens
                "RECIPE_ACQUISITION":"default",
                "RECIPE_YIELD": 1,
                "ING1":"637",
                "ING1_COUNT":"3",
                "ING2":"245",
                "ING2_COUNT": 1,
                "ING3":"",
                "ING3_COUNT":"",
                "ING4":"",
                "ING4_COUNT":"",
                "ING5":"",
                "ING5_COUNT":"",
            }
        },
        {
            "LogName": "Object Data Tokens - Mango Syrup",
            "Action": "Include",
            "FromFile": "Data/Templates/Objects.json, Data/Templates/{{Method}}.json",
            "LocalTokens": {
                "MACHINE_TYPE": "{{ModId}}_SyrupMaker",
                "ITEM_TYPE": "Syrup",
                "ITEM_FLAVOR":"Mango",
                "INPUT1":"id_(O)834",
                "INPUT1_COUNT":3,
                "INPUT2":"",
                "PRICE_MULTIPLIER": 3.25,
                "PRICE_ADDER": 0,
                "MINUTES_UNTIL_READY": 20,
                "OBJECT_TYPE":"ArtisanGoods",
                "OBJECT_CATEGORY":-26,
                "OBJECT_PRICE":528,
                "EDIBILITY":0,
                "DRINKABILITY":false,
                "ITEM_SPRITE":87,
                 //hybrid tokens
                "RECIPE_ACQUISITION":"default",
                "RECIPE_YIELD": 1,
                "ING1":"834",
                "ING1_COUNT":"3",
                "ING2":"245",
                "ING2_COUNT": 1,
                "ING3":"",
                "ING3_COUNT":"",
                "ING4":"",
                "ING4_COUNT":"",
                "ING5":"",
                "ING5_COUNT":"",
            }
        },
        {
            "LogName": "Object Data Tokens - Orange Syrup",
            "Action": "Include",
            "FromFile": "Data/Templates/Objects.json, Data/Templates/{{Method}}.json",
            "LocalTokens": {
                "MACHINE_TYPE": "{{ModId}}_SyrupMaker",
                "ITEM_TYPE": "Syrup",
                "ITEM_FLAVOR":"Orange",
                "INPUT1":"id_(O)635",
                "INPUT1_COUNT":3,
                "INPUT2":"",
                "PRICE_MULTIPLIER": 3.25,
                "PRICE_ADDER": 0,
                "MINUTES_UNTIL_READY": 20,
                "OBJECT_TYPE":"ArtisanGoods",
                "OBJECT_CATEGORY":-26,
                "OBJECT_PRICE":456,
                "EDIBILITY":0,
                "DRINKABILITY":false,
                "ITEM_SPRITE":88,
                 //hybrid tokens
                "RECIPE_ACQUISITION":"default",
                "RECIPE_YIELD": 1,
                "ING1":"635",
                "ING1_COUNT":"3",
                "ING2":"245",
                "ING2_COUNT": 1,
                "ING3":"",
                "ING3_COUNT":"",
                "ING4":"",
                "ING4_COUNT":"",
                "ING5":"",
                "ING5_COUNT":"",
            }
        },
        {
            "LogName": "Object Data Tokens - Peach Syrup",
            "Action": "Include",
            "FromFile": "Data/Templates/Objects.json, Data/Templates/{{Method}}.json",
            "LocalTokens": {
                "MACHINE_TYPE": "{{ModId}}_SyrupMaker",
                "ITEM_TYPE": "Syrup",
                "ITEM_FLAVOR":"Peach",
                "INPUT1":"id_(O)636",
                "INPUT1_COUNT":3,
                "INPUT2":"",
                "PRICE_MULTIPLIER": 3.25,
                "PRICE_ADDER": 0,
                "MINUTES_UNTIL_READY": 20,
                "OBJECT_TYPE":"ArtisanGoods",
                "OBJECT_CATEGORY":-26,
                "OBJECT_PRICE":564,
                "EDIBILITY":0,
                "DRINKABILITY":false,
                "ITEM_SPRITE":89,
                 //hybrid tokens
                "RECIPE_ACQUISITION":"default",
                "RECIPE_YIELD": 1,
                "ING1":"636",
                "ING1_COUNT":"3",
                "ING2":"245",
                "ING2_COUNT": 1,
                "ING3":"",
                "ING3_COUNT":"",
                "ING4":"",
                "ING4_COUNT":"",
                "ING5":"",
                "ING5_COUNT":"",
            }
        },
        {
            "LogName": "Object Data Tokens - Pumpkin Syrup",
            "Action": "Include",
            "FromFile": "Data/Templates/Objects.json, Data/Templates/{{Method}}.json",
            "LocalTokens": {
                "MACHINE_TYPE": "{{ModId}}_SyrupMaker",
                "ITEM_TYPE": "Syrup",
                "ITEM_FLAVOR":"Pumpkin",
                "INPUT1":"id_(O)276",
                "INPUT1_COUNT":3,
                "INPUT2":"",
                "PRICE_MULTIPLIER": 3.25,
                "PRICE_ADDER": 0,
                "MINUTES_UNTIL_READY": 20,
                "OBJECT_TYPE":"ArtisanGoods",
                "OBJECT_CATEGORY":-26,
                "OBJECT_PRICE":1212,
                "EDIBILITY":0,
                "DRINKABILITY":false,
                "ITEM_SPRITE":90,
                 //hybrid tokens
                "RECIPE_ACQUISITION":"default",
                "RECIPE_YIELD": 1,
                "ING1":"276",
                "ING1_COUNT":"3",
                "ING2":"245",
                "ING2_COUNT": 1,
                "ING3":"",
                "ING3_COUNT":"",
                "ING4":"",
                "ING4_COUNT":"",
                "ING5":"",
                "ING5_COUNT":"",
            }
        },
        {
            "LogName": "Object Data Tokens - Strawberry Syrup",
            "Action": "Include",
            "FromFile": "Data/Templates/Objects.json, Data/Templates/{{Method}}.json",
            "LocalTokens": {
                "MACHINE_TYPE": "{{ModId}}_SyrupMaker",
                "ITEM_TYPE": "Syrup",
                "ITEM_FLAVOR":"Strawberry",
                "INPUT1":"id_(O)400",
                "INPUT1_COUNT":3,
                "INPUT2":"",
                "PRICE_MULTIPLIER": 3.25,
                "PRICE_ADDER": 0,
                "MINUTES_UNTIL_READY": 20,
                "OBJECT_TYPE":"ArtisanGoods",
                "OBJECT_CATEGORY":-26,
                "OBJECT_PRICE":492,
                "EDIBILITY":0,
                "DRINKABILITY":false,
                "ITEM_SPRITE":92,
                 //hybrid tokens
                "RECIPE_ACQUISITION":"default",
                "RECIPE_YIELD": 1,
                "ING1":"400",
                "ING1_COUNT":"3",
                "ING2":"245",
                "ING2_COUNT": 1,
                "ING3":"",
                "ING3_COUNT":"",
                "ING4":"",
                "ING4_COUNT":"",
                "ING5":"",
                "ING5_COUNT":"",
            }
        },

        {
            "LogName": "Object Data Tokens - Caramel",
            "Action": "Include",
            "FromFile": "Data/Templates/Objects.json, Data/Templates/{{Method}}.json",
            "LocalTokens": {
                "MACHINE_TYPE": "{{ModId}}_SyrupMaker",
                "ITEM_TYPE": "Syrup",
                "ITEM_FLAVOR":"Caramel",
                "INPUT1":"id_(O){{ModId}}_Brown_Sugar",
                "INPUT1_COUNT":3,
                "INPUT2":"",
                "PRICE_MULTIPLIER": 3.25,
                "PRICE_ADDER": 0,
                "MINUTES_UNTIL_READY": 20,
                "OBJECT_TYPE":"ArtisanGoods",
                "OBJECT_CATEGORY":-26,
                "OBJECT_PRICE":924,
                "EDIBILITY":0,
                "DRINKABILITY":false,
                "ITEM_SPRITE":607,
                 //hybrid tokens
                "RECIPE_ACQUISITION":"default",
                "RECIPE_YIELD": 1,
                "ING1":"{{ModId}}_Brown_Sugar",
                "ING1_COUNT":"3",
                "ING2":"245",
                "ING2_COUNT": 1,
                "ING3":"",
                "ING3_COUNT":"",
                "ING4":"",
                "ING4_COUNT":"",
                "ING5":"",
                "ING5_COUNT":"",
            }
        },

        {
            "LogName": "Object Data Tokens - Cherry_Blossom Syrup",
            "Action": "Include",
            "FromFile": "Data/Templates/Objects.json, Data/Templates/{{Method}}.json",
            "When": {"Atelier.Cauldron/ConfigValue:WildFood":true},
            "LocalTokens": {
                "MACHINE_TYPE": "{{ModId}}_SyrupMaker",
                "ITEM_TYPE": "Syrup",
                "ITEM_FLAVOR":"Cherry_Blossom",
                "INPUT1":"id_(O){{ModId}}_Cherry_Blossoms",
                "INPUT1_COUNT":3,
                "INPUT2":"",
                "PRICE_MULTIPLIER": 4,
                "PRICE_ADDER": 0,
                "MINUTES_UNTIL_READY": 240,
                "OBJECT_TYPE":"ArtisanGoods",
                "OBJECT_CATEGORY":-26,
                "OBJECT_PRICE":114,
                "EDIBILITY":0,
                "DRINKABILITY":false,
                "ITEM_SPRITE":107,
                 //hybrid tokens
                "RECIPE_ACQUISITION":"default",
                "RECIPE_YIELD": 1,
                "ING1":"{{ModId}}_Cherry_Blossoms",
                "ING1_COUNT":"3",
                "ING2":"245",
                "ING2_COUNT": 1,
                "ING3":"",
                "ING3_COUNT":"",
                "ING4":"",
                "ING4_COUNT":"",
                "ING5":"",
                "ING5_COUNT":"",
            }
        },
        {
            "LogName": "Object Data Tokens - Chocolate Syrup",
            "Action": "Include",
            "FromFile": "Data/Templates/Objects.json, Data/Templates/{{Method}}.json",
            "When": {"Atelier.Cauldron/ConfigValue:WildFood":true},
            "LocalTokens": {
                "MACHINE_TYPE": "{{ModId}}_SyrupMaker",
                "ITEM_TYPE": "Syrup",
                "ITEM_FLAVOR":"Chocolate",
                "INPUT1":"cocoa_item",
                "INPUT1_COUNT":3,
                "INPUT2":"",
                "PRICE_MULTIPLIER": 4,
                "PRICE_ADDER": 0,
                "MINUTES_UNTIL_READY": 240,
                "OBJECT_TYPE":"ArtisanGoods",
                "OBJECT_CATEGORY":-26,
                "OBJECT_PRICE":870,
                "EDIBILITY":0,
                "DRINKABILITY":false,
                "ITEM_SPRITE":108,
                 //hybrid tokens
                "RECIPE_ACQUISITION":"default",
                "RECIPE_YIELD": 1,
                "ING1":"{{ModId}}_Cacao_Pod",
                "ING1_COUNT":"3",
                "ING2":"245",
                "ING2_COUNT": 1,
                "ING3":"",
                "ING3_COUNT":"",
                "ING4":"",
                "ING4_COUNT":"",
                "ING5":"",
                "ING5_COUNT":"",
            }
        },

        {
            "LogName": "Object Data Tokens - Lemon Syrup",
            "Action": "Include",
            "FromFile": "Data/Templates/Objects.json, Data/Templates/{{Method}}.json",
            "When": {"Atelier.Cauldron/ConfigValue:WildFood":true},
            "LocalTokens": {
                "MACHINE_TYPE": "{{ModId}}_SyrupMaker",
                "ITEM_TYPE": "Syrup",
                "ITEM_FLAVOR":"Lemon",
                "INPUT1":"lemon_item",
                "INPUT1_COUNT":3,
                "INPUT2":"",
                "PRICE_MULTIPLIER": 4,
                "PRICE_ADDER": 0,
                "MINUTES_UNTIL_READY": 240,
                "OBJECT_TYPE":"ArtisanGoods",
                "OBJECT_CATEGORY":-26,
                "OBJECT_PRICE":510,
                "EDIBILITY":0,
                "DRINKABILITY":false,
                "ITEM_SPRITE":110,
                 //hybrid tokens
                "RECIPE_ACQUISITION":"default",
                "RECIPE_YIELD": 1,
                "ING1":"{{ModId}}_Lemon",
                "ING1_COUNT":"3",
                "ING2":"245",
                "ING2_COUNT": 1,
                "ING3":"",
                "ING3_COUNT":"",
                "ING4":"",
                "ING4_COUNT":"",
                "ING5":"",
                "ING5_COUNT":"",
            }
        },
        {
            "LogName": "Object Data Tokens - Lime Syrup",
            "Action": "Include",
            "FromFile": "Data/Templates/Objects.json, Data/Templates/{{Method}}.json",
            "When": {"Atelier.Cauldron/ConfigValue:WildFood":true},
            "LocalTokens": {
                "MACHINE_TYPE": "{{ModId}}_SyrupMaker",
                "ITEM_TYPE": "Syrup",
                "ITEM_FLAVOR":"Lime",
                "INPUT1":"lime_item",
                "INPUT1_COUNT":3,
                "INPUT2":"",
                "PRICE_MULTIPLIER": 4,
                "PRICE_ADDER": 0,
                "MINUTES_UNTIL_READY": 240,
                "OBJECT_TYPE":"ArtisanGoods",
                "OBJECT_CATEGORY":-26,
                "OBJECT_PRICE":474,
                "EDIBILITY":0,
                "DRINKABILITY":false,
                "ITEM_SPRITE":111,
                 //hybrid tokens
                "RECIPE_ACQUISITION":"default",
                "RECIPE_YIELD": 1,
                "ING1":"{{ModId}}_Lime",
                "ING1_COUNT":"3",
                "ING2":"245",
                "ING2_COUNT": 1,
                "ING3":"",
                "ING3_COUNT":"",
                "ING4":"",
                "ING4_COUNT":"",
                "ING5":"",
                "ING5_COUNT":"",
            }
        },
        {
            "LogName": "Object Data Tokens - Raspberry Syrup",
            "Action": "Include",
            "FromFile": "Data/Templates/Objects.json, Data/Templates/{{Method}}.json",
            "When": {"Atelier.Cauldron/ConfigValue:WildFood":true},
            "LocalTokens": {
                "MACHINE_TYPE": "{{ModId}}_SyrupMaker",
                "ITEM_TYPE": "Syrup",
                "ITEM_FLAVOR":"Raspberry",
                "INPUT1":"raspberry_item",
                "INPUT1_COUNT":3,
                "INPUT2":"",
                "PRICE_MULTIPLIER": 4,
                "PRICE_ADDER": 0,
                "MINUTES_UNTIL_READY": 240,
                "OBJECT_TYPE":"ArtisanGoods",
                "OBJECT_CATEGORY":-26,
                "OBJECT_PRICE":132,
                "EDIBILITY":0,
                "DRINKABILITY":false,
                "ITEM_SPRITE":112,
                 //hybrid tokens
                "RECIPE_ACQUISITION":"default",
                "RECIPE_YIELD": 1,
                "ING1":"{{ModId}}_Wild_Raspberry",
                "ING1_COUNT":"3",
                "ING2":"245",
                "ING2_COUNT": 1,
                "ING3":"",
                "ING3_COUNT":"",
                "ING4":"",
                "ING4_COUNT":"",
                "ING5":"",
                "ING5_COUNT":"",
            }
        },
        {
            "LogName": "Object Data Tokens - Vanilla Syrup",
            "Action": "Include",
            "FromFile": "Data/Templates/Objects.json, Data/Templates/{{Method}}.json",
            "When": {"Atelier.Cauldron/ConfigValue:WildFood":true},
            "LocalTokens": {
                "MACHINE_TYPE": "{{ModId}}_SyrupMaker",
                "ITEM_TYPE": "Syrup",
                "ITEM_FLAVOR":"Vanilla",
                "INPUT1":"vanilla_item",
                "INPUT1_COUNT":3,
                "INPUT2":"",
                "PRICE_MULTIPLIER": 4,
                "PRICE_ADDER": 0,
                "MINUTES_UNTIL_READY": 240,
                "OBJECT_TYPE":"ArtisanGoods",
                "OBJECT_CATEGORY":-26,
                "OBJECT_PRICE":546,
                "EDIBILITY":0,
                "DRINKABILITY":false,
                "ITEM_SPRITE":113,
                 //hybrid tokens
                "RECIPE_ACQUISITION":"default",
                "RECIPE_YIELD": 1,
                "ING1":"{{ModId}}_Vanilla",
                "ING1_COUNT":"3",
                "ING2":"245",
                "ING2_COUNT": 1,
                "ING3":"",
                "ING3_COUNT":"",
                "ING4":"",
                "ING4_COUNT":"",
                "ING5":"",
                "ING5_COUNT":"",
            }
        },

//simple mode flavored syrup

        {
            "LogName": "Object Data Tokens - Flavored Syrup",
            "Action": "Include",
            "FromFile": "Data/Templates/Objects.json, Data/Templates/Simple.json",
            "When": {"Query:('{{Atelier.Cauldron/ConfigValue:SimpleAddOn}}' ='true') OR ('{{Atelier.Cauldron/ConfigValue:DifficultyToggle}}'='Simple')":true},
            "LocalTokens": {
                "MACHINE_TYPE": "{{ModId}}_SyrupMaker",
                "ITEM_TYPE": "Syrup",
                "ITEM_FLAVOR":"Flavored",
                "INPUT_TYPE":"",
                "PRICE_MULTIPLIER": 4,
                "PRICE_ADDER": 0,
                "MINUTES_UNTIL_READY": 240,
                "OBJECT_TYPE":"ArtisanGoods",
                "OBJECT_CATEGORY":-26,
                "OBJECT_PRICE":100,
                "EDIBILITY":20,
                "DRINKABILITY":false,
                "ITEM_SPRITE":93,
                 //hybrid tokens
                "RECIPE_ACQUISITION":"default",
                "RECIPE_YIELD": 1,
                "ING1":"",
                "ING1_COUNT":"3",
                "ING2":"245",
                "ING2_COUNT": 1,
                "ING3":"",
                "ING3_COUNT":"",
                "ING4":"",
                "ING4_COUNT":"",
                "ING5":"",
                "ING5_COUNT":"",
            }
        },

//new in 3.0 juices and liquors from mixology

        {
            "LogName": "Object Data Tokens - Lemon Juice",
            "Action": "Include",
            "FromFile": "Data/Templates/Objects.json, Data/Templates/{{Method}}.json",
            "LocalTokens": {
                "MACHINE_TYPE": "{{ModId}}_KitchenBlender",
                "ITEM_TYPE": "Juice",
                "ITEM_FLAVOR":"Lemon",
                "INPUT1":"id_(O)",
                "INPUT1_COUNT":1,
                "INPUT2":"",
                "PRICE_MULTIPLIER": 1.2,
                "PRICE_ADDER": 0,
                "MINUTES_UNTIL_READY": 20,
                "OBJECT_TYPE":"ArtisanGoods",
                "OBJECT_CATEGORY":-26,
                "OBJECT_PRICE":300,
                "EDIBILITY":20,
                "DRINKABILITY":false,
                "ITEM_SPRITE":821,
                 //hybrid tokens
                "RECIPE_ACQUISITION":"default",
                "RECIPE_YIELD": 1,
                "ING1":"{{ModId}}_Lemon",
                "ING1_COUNT":"2",
                "ING2":"",
                "ING2_COUNT":"",
                "ING3":"",
                "ING3_COUNT":"",
                "ING4":"",
                "ING4_COUNT":"",
                "ING5":"",
                "ING5_COUNT":"",
            }
        },
        {
            "LogName": "Object Data Tokens - Cranberry Juice",
            "Action": "Include",
            "FromFile": "Data/Templates/Objects.json, Data/Templates/{{Method}}.json",
            "LocalTokens": {
                "MACHINE_TYPE": "{{ModId}}_KitchenBlender",
                "ITEM_TYPE": "Juice",
                "ITEM_FLAVOR":"Cranberry",
                "INPUT1":"id_(O)282",
                "INPUT1_COUNT":1,
                "INPUT2":"",
                "PRICE_MULTIPLIER": 1.2,
                "PRICE_ADDER": 0,
                "MINUTES_UNTIL_READY": 20,
                "OBJECT_TYPE":"ArtisanGoods",
                "OBJECT_CATEGORY":-26,
                "OBJECT_PRICE":180,
                "EDIBILITY":20,
                "DRINKABILITY":false,
                "ITEM_SPRITE":820,
                 //hybrid tokens
                "RECIPE_ACQUISITION":"default",
                "RECIPE_YIELD": 1,
                "ING1":"282",
                "ING1_COUNT":"",
                "ING2":"",
                "ING2_COUNT":"",
                "ING3":"",
                "ING3_COUNT":"",
                "ING4":"",
                "ING4_COUNT":"",
                "ING5":"",
                "ING5_COUNT":"",
            }
        },
        {
            "LogName": "Object Data Tokens - Lime Juice",
            "Action": "Include",
            "FromFile": "Data/Templates/Objects.json, Data/Templates/{{Method}}.json",
            "LocalTokens": {
                "MACHINE_TYPE": "{{ModId}}_KitchenBlender",
                "ITEM_TYPE": "Juice",
                "ITEM_FLAVOR":"Lime",
                "INPUT1":"id_(O){{ModId}}_Lime",
                "INPUT1_COUNT":1,
                "INPUT2":"",
                "PRICE_MULTIPLIER": 1.2,
                "PRICE_ADDER": 0,
                "MINUTES_UNTIL_READY": 20,
                "OBJECT_TYPE":"ArtisanGoods",
                "OBJECT_CATEGORY":-26,
                "OBJECT_PRICE":276,
                "EDIBILITY":20,
                "DRINKABILITY":false,
                "ITEM_SPRITE":822,
                 //hybrid tokens
                "RECIPE_ACQUISITION":"default",
                "RECIPE_YIELD": 1,
                "ING1":"{{ModId}}_Lime",
                "ING1_COUNT":"2",
                "ING2":"",
                "ING2_COUNT":"",
                "ING3":"",
                "ING3_COUNT":"",
                "ING4":"",
                "ING4_COUNT":"",
                "ING5":"",
                "ING5_COUNT":"",
            }
        },
        {
            "LogName": "Object Data Tokens - Orange Juice",
            "Action": "Include",
            "FromFile": "Data/Templates/Objects.json, Data/Templates/{{Method}}.json",
            "LocalTokens": {
                "MACHINE_TYPE": "{{ModId}}_KitchenBlender",
                "ITEM_TYPE": "Juice",
                "ITEM_FLAVOR":"Orange",
                "INPUT1":"id_(O)635",
                "INPUT1_COUNT":1,
                "INPUT2":"",
                "PRICE_MULTIPLIER": 1.2,
                "PRICE_ADDER": 0,
                "MINUTES_UNTIL_READY": 20,
                "OBJECT_TYPE":"ArtisanGoods",
                "OBJECT_CATEGORY":-26,
                "OBJECT_PRICE":264,
                "EDIBILITY":20,
                "DRINKABILITY":false,
                "ITEM_SPRITE":823,
                 //hybrid tokens
                "RECIPE_ACQUISITION":"default",
                "RECIPE_YIELD": 1,
                "ING1":"635",
                "ING1_COUNT":"2",
                "ING2":"",
                "ING2_COUNT":"",
                "ING3":"",
                "ING3_COUNT":"",
                "ING4":"",
                "ING4_COUNT":"",
                "ING5":"",
                "ING5_COUNT":"",
            }
        },
        {
            "LogName": "Object Data Tokens - Pineapple Juice",
            "Action": "Include",
            "FromFile": "Data/Templates/Objects.json, Data/Templates/{{Method}}.json",
            "LocalTokens": {
                "MACHINE_TYPE": "{{ModId}}_KitchenBlender",
                "ITEM_TYPE": "Juice",
                "ITEM_FLAVOR":"Pineapple",
                "INPUT1":"id_(O)832",
                "INPUT1_COUNT":1,
                "INPUT2":"",
                "PRICE_MULTIPLIER": 1.2,
                "PRICE_ADDER": 0,
                "MINUTES_UNTIL_READY": 20,
                "OBJECT_TYPE":"ArtisanGoods",
                "OBJECT_CATEGORY":-26,
                "OBJECT_PRICE":720,
                "EDIBILITY":20,
                "DRINKABILITY":false,
                "ITEM_SPRITE":824,
                 //hybrid tokens
                "RECIPE_ACQUISITION":"default",
                "RECIPE_YIELD": 1,
                "ING1":"832",
                "ING1_COUNT":"2",
                "ING2":"",
                "ING2_COUNT":"",
                "ING3":"",
                "ING3_COUNT":"",
                "ING4":"",
                "ING4_COUNT":"",
                "ING5":"",
                "ING5_COUNT":"",
            }
        },
        {
            "LogName": "Object Data Tokens - Apple Juice",
            "Action": "Include",
            "FromFile": "Data/Templates/Objects.json, Data/Templates/{{Method}}.json",
            "LocalTokens": {
                "MACHINE_TYPE": "{{ModId}}_KitchenBlender",
                "ITEM_TYPE": "Juice",
                "ITEM_FLAVOR":"Apple",
                "INPUT1":"id_(O)613",
                "INPUT1_COUNT":1,
                "INPUT2":"",
                "PRICE_MULTIPLIER": 1.2,
                "PRICE_ADDER": 0,
                "MINUTES_UNTIL_READY": 20,
                "OBJECT_TYPE":"ArtisanGoods",
                "OBJECT_CATEGORY":-26,
                "OBJECT_PRICE":720,
                "EDIBILITY":20,
                "DRINKABILITY":false,
                "ITEM_SPRITE":904,
                 //hybrid tokens
                "RECIPE_ACQUISITION":"default",
                "RECIPE_YIELD": 1,
                "ING1":"613",
                "ING1_COUNT":"2",
                "ING2":"",
                "ING2_COUNT":"",
                "ING3":"",
                "ING3_COUNT":"",
                "ING4":"",
                "ING4_COUNT":"",
                "ING5":"",
                "ING5_COUNT":"",
            }
        },
        {
            "LogName": "Object Data Tokens - Berry Juice",
            "Action": "Include",
            "FromFile": "Data/Templates/Objects.json, Data/Templates/{{Method}}.json",
            "LocalTokens": {
                "MACHINE_TYPE": "{{ModId}}_KitchenBlender",
                "ITEM_TYPE": "Juice",
                "ITEM_FLAVOR":"Pineapple",
                "INPUT1":"id_(O)832",
                "INPUT1_COUNT":1,
                "INPUT2":"",
                "PRICE_MULTIPLIER": 1.2,
                "PRICE_ADDER": 0,
                "MINUTES_UNTIL_READY": 20,
                "OBJECT_TYPE":"ArtisanGoods",
                "OBJECT_CATEGORY":-26,
                "OBJECT_PRICE":720,
                "EDIBILITY":20,
                "DRINKABILITY":false,
                "ITEM_SPRITE":902,
                 //hybrid tokens
                "RECIPE_ACQUISITION":"default",
                "RECIPE_YIELD": 1,
                "ING1":"{{ModId}}_Wild_Raspberry",
                "ING1_COUNT":"2",
                "ING2":"",
                "ING2_COUNT":"",
                "ING3":"",
                "ING3_COUNT":"",
                "ING4":"",
                "ING4_COUNT":"",
                "ING5":"",
                "ING5_COUNT":"",
            }
        },
        {
            "LogName": "Object Data Tokens - Mango Juice",
            "Action": "Include",
            "FromFile": "Data/Templates/Objects.json, Data/Templates/{{Method}}.json",
            "LocalTokens": {
                "MACHINE_TYPE": "{{ModId}}_KitchenBlender",
                "ITEM_TYPE": "Juice",
                "ITEM_FLAVOR":"Mango",
                "INPUT1":"id_(O)832",
                "INPUT1_COUNT":1,
                "INPUT2":"",
                "PRICE_MULTIPLIER": 1.2,
                "PRICE_ADDER": 0,
                "MINUTES_UNTIL_READY": 20,
                "OBJECT_TYPE":"ArtisanGoods",
                "OBJECT_CATEGORY":-26,
                "OBJECT_PRICE":720,
                "EDIBILITY":20,
                "DRINKABILITY":false,
                "ITEM_SPRITE":905,
                 //hybrid tokens
                "RECIPE_ACQUISITION":"default",
                "RECIPE_YIELD": 1,
                "ING1":"832",
                "ING1_COUNT":"2",
                "ING2":"",
                "ING2_COUNT":"",
                "ING3":"",
                "ING3_COUNT":"",
                "ING4":"",
                "ING4_COUNT":"",
                "ING5":"",
                "ING5_COUNT":"",
            }
        },
        {
            "LogName": "Object Data Tokens - Pomegranate Juice",
            "Action": "Include",
            "FromFile": "Data/Templates/Objects.json, Data/Templates/{{Method}}.json",
            "LocalTokens": {
                "MACHINE_TYPE": "{{ModId}}_KitchenBlender",
                "ITEM_TYPE": "Juice",
                "ITEM_FLAVOR":"Pomegranate",
                "INPUT1":"id_(O)832",
                "INPUT1_COUNT":1,
                "INPUT2":"",
                "PRICE_MULTIPLIER": 1.2,
                "PRICE_ADDER": 0,
                "MINUTES_UNTIL_READY": 20,
                "OBJECT_TYPE":"ArtisanGoods",
                "OBJECT_CATEGORY":-26,
                "OBJECT_PRICE":720,
                "EDIBILITY":20,
                "DRINKABILITY":false,
                "ITEM_SPRITE":902,
                 //hybrid tokens
                "RECIPE_ACQUISITION":"default",
                "RECIPE_YIELD": 1,
                "ING1":"832",
                "ING1_COUNT":"2",
                "ING2":"",
                "ING2_COUNT":"",
                "ING3":"",
                "ING3_COUNT":"",
                "ING4":"",
                "ING4_COUNT":"",
                "ING5":"",
                "ING5_COUNT":"",
            }
        },
          {
            "LogName": "Object Data Tokens - Coconut Water",
            "Action": "Include",
            "FromFile": "Data/Templates/Objects.json, Data/Templates/{{Method}}.json",
            "LocalTokens": {
                "MACHINE_TYPE": "{{ModId}}_KitchenBlender",
                "ITEM_TYPE": "Water",
                "ITEM_FLAVOR":"Coconut",
                "INPUT1":"id_(O)88",
                "INPUT1_COUNT":3,
                "INPUT2":"",
                "PRICE_MULTIPLIER": 1.2,
                "PRICE_ADDER": 0,
                "MINUTES_UNTIL_READY": 20,
                "OBJECT_TYPE":"ArtisanGoods",
                "OBJECT_CATEGORY":-26,
                "OBJECT_PRICE":720,
                "EDIBILITY":20,
                "DRINKABILITY":false,
                "ITEM_SPRITE":906,
                 //hybrid tokens
                "RECIPE_ACQUISITION":"default",
                "RECIPE_YIELD": 1,
                "ING1":"88",
                "ING1_COUNT":"2",
                "ING2":"",
                "ING2_COUNT":"",
                "ING3":"",
                "ING3_COUNT":"",
                "ING4":"",
                "ING4_COUNT":"",
                "ING5":"",
                "ING5_COUNT":"",
            }
        },

        {
            "LogName": "Object Data Tokens - Club Soda",
            "Action": "Include",
            "FromFile": "Data/Templates/Objects.json, Data/Templates/{{Method}}.json",
            "LocalTokens": {
                "MACHINE_TYPE": "{{ModId}}_KitchenBlender",
                "ITEM_TYPE": "Soda",
                "ITEM_FLAVOR":"Club",
                "INPUT1":"id_(O)167",
                "INPUT1_COUNT":1,
                "INPUT2":"",
                "PRICE_MULTIPLIER": 1.2,
                "PRICE_ADDER": 0,
                "MINUTES_UNTIL_READY": 20,
                "OBJECT_TYPE":"ArtisanGoods",
                "OBJECT_CATEGORY":-26,
                "OBJECT_PRICE":100,
                "EDIBILITY":20,
                "DRINKABILITY":false,
                "ITEM_SPRITE":819,
                 //hybrid tokens
                "RECIPE_ACQUISITION":"default",
                "RECIPE_YIELD": 1,
                "ING1":"167",
                "ING1_COUNT": 1,
                "ING2":"",
                "ING2_COUNT":"",
                "ING3":"",
                "ING3_COUNT":"",
                "ING4":"",
                "ING4_COUNT":"",
                "ING5":"",
                "ING5_COUNT":"",
            }
        },
        {
            "LogName": "Object Data Tokens - Tonic Water",
            "Action": "Include",
            "FromFile": "Data/Templates/Objects.json, Data/Templates/{{Method}}.json",
            "LocalTokens": {
                "MACHINE_TYPE": "{{ModId}}_KitchenBlender",
                "ITEM_TYPE": "Water",
                "ITEM_FLAVOR":"Tonic",
                "INPUT1":"id_(O)80",
                "INPUT1_COUNT":1,
                "INPUT2":"",
                "PRICE_MULTIPLIER": 1.2,
                "PRICE_ADDER": 0,
                "MINUTES_UNTIL_READY": 20,
                "OBJECT_TYPE":"ArtisanGoods",
                "OBJECT_CATEGORY":-26,
                "OBJECT_PRICE":100,
                "EDIBILITY":20,
                "DRINKABILITY":false,
                "ITEM_SPRITE":825,
                 //hybrid tokens
                "RECIPE_ACQUISITION":"default",
                "RECIPE_YIELD": 1,
                "ING1":"80",
                "ING1_COUNT": 1,
                "ING2":"",
                "ING2_COUNT":"",
                "ING3":"",
                "ING3_COUNT":"",
                "ING4":"",
                "ING4_COUNT":"",
                "ING5":"",
                "ING5_COUNT":"",
            }
        },
//mixology alcohols
        {
            "LogName": "Object Data Tokens - Brandy",
            "Action": "Include",
            "FromFile": "Data/Templates/Objects.json, Data/Templates/{{Method}}.json",
            "LocalTokens": {
                "MACHINE_TYPE": "{{ModId}}_SyrupMaker",
                "ITEM_TYPE": "Alcohol",
                "ITEM_FLAVOR":"Brandy",
                "INPUT1":"id_(O)348",
                "INPUT1_COUNT":2,
                "INPUT2":"",
                "PRICE_MULTIPLIER": 1.2,
                "PRICE_ADDER": 0,
                "MINUTES_UNTIL_READY": 20,
                "OBJECT_TYPE":"ArtisanGoods",
                "OBJECT_CATEGORY":-26,
                "OBJECT_PRICE":960,
                "EDIBILITY":20,
                "DRINKABILITY":false,
                "ITEM_SPRITE":827,
                 //hybrid tokens
                "RECIPE_ACQUISITION":"default",
                "RECIPE_YIELD": 1,
                "ING1":"348",
                "ING1_COUNT":"2",
                "ING2":"",
                "ING2_COUNT":"",
                "ING3":"",
                "ING3_COUNT":"",
                "ING4":"",
                "ING4_COUNT":"",
                "ING5":"",
                "ING5_COUNT":"",
            }
        },
        {
            "LogName": "Object Data Tokens - Gin",
            "Action": "Include",
            "FromFile": "Data/Templates/Objects.json, Data/Templates/{{Method}}.json",
            "LocalTokens": {
                "MACHINE_TYPE": "{{ModId}}_SyrupMaker",
                "ITEM_TYPE": "Alcohol",
                "ITEM_FLAVOR":"Gin",
                "INPUT1":"id_(O)262",
                "INPUT1_COUNT":2,
                "INPUT2":"",
                "PRICE_MULTIPLIER": 1.2,
                "PRICE_ADDER": 0,
                "MINUTES_UNTIL_READY": 20,
                "OBJECT_TYPE":"ArtisanGoods",
                "OBJECT_CATEGORY":-26,
                "OBJECT_PRICE":60,
                "EDIBILITY":20,
                "DRINKABILITY":false,
                "ITEM_SPRITE":830,
                 //hybrid tokens
                "RECIPE_ACQUISITION":"default",
                "RECIPE_YIELD": 1,
                "ING1":"262",
                "ING1_COUNT":"2",
                "ING2":"",
                "ING2_COUNT":"",
                "ING3":"",
                "ING3_COUNT":"",
                "ING4":"",
                "ING4_COUNT":"",
                "ING5":"",
                "ING5_COUNT":"",
            }
        },
        {
            "LogName": "Object Data Tokens - Rum",
            "Action": "Include",
            "FromFile": "Data/Templates/Objects.json, Data/Templates/{{Method}}.json",
            "LocalTokens": {
                "MACHINE_TYPE": "{{ModId}}_SyrupMaker",
                "ITEM_TYPE": "Alcohol",
                "ITEM_FLAVOR":"Rum",
                "INPUT1":"id_(O)724",
                "INPUT1_COUNT":2,
                "INPUT2":"",
                "PRICE_MULTIPLIER": 1.2,
                "PRICE_ADDER": 0,
                "MINUTES_UNTIL_READY": 20,
                "OBJECT_TYPE":"ArtisanGoods",
                "OBJECT_CATEGORY":-26,
                "OBJECT_PRICE":480,
                "EDIBILITY":20,
                "DRINKABILITY":false,
                "ITEM_SPRITE":832,
                 //hybrid tokens
                "RECIPE_ACQUISITION":"default",
                "RECIPE_YIELD": 1,
                "ING1":"724",
                "ING1_COUNT":"2",
                "ING2":"",
                "ING2_COUNT":"",
                "ING3":"",
                "ING3_COUNT":"",
                "ING4":"",
                "ING4_COUNT":"",
                "ING5":"",
                "ING5_COUNT":"",
            }
        },
        {
            "LogName": "Object Data Tokens - Tequila",
            "Action": "Include",
            "FromFile": "Data/Templates/Objects.json, Data/Templates/{{Method}}.json",
            "LocalTokens": {
                "MACHINE_TYPE": "{{ModId}}_SyrupMaker",
                "ITEM_TYPE": "Alcohol",
                "ITEM_FLAVOR":"Tequila",
                "INPUT1":"id_(O)90",
                "INPUT1_COUNT":2,
                "INPUT2":"",
                "PRICE_MULTIPLIER": 1.2,
                "PRICE_ADDER": 0,
                "MINUTES_UNTIL_READY": 20,
                "OBJECT_TYPE":"ArtisanGoods",
                "OBJECT_CATEGORY":-26,
                "OBJECT_PRICE":180,
                "EDIBILITY":20,
                "DRINKABILITY":false,
                "ITEM_SPRITE":834,
                 //hybrid tokens
                "RECIPE_ACQUISITION":"default",
                "RECIPE_YIELD": 1,
                "ING1":"90",
                "ING1_COUNT":"2",
                "ING2":"",
                "ING2_COUNT":"",
                "ING3":"",
                "ING3_COUNT":"",
                "ING4":"",
                "ING4_COUNT":"",
                "ING5":"",
                "ING5_COUNT":"",
            }
        },
        {
            "LogName": "Object Data Tokens - Vodka",
            "Action": "Include",
            "FromFile": "Data/Templates/Objects.json, Data/Templates/{{Method}}.json",
            "LocalTokens": {
                "MACHINE_TYPE": "{{ModId}}_SyrupMaker",
                "ITEM_TYPE": "Alcohol",
                "ITEM_FLAVOR":"Vodka",
                "INPUT1":"id_(O)192",
                "INPUT1_COUNT":2,
                "INPUT2":"",
                "PRICE_MULTIPLIER": 1.2,
                "PRICE_ADDER": 0,
                "MINUTES_UNTIL_READY": 20,
                "OBJECT_TYPE":"ArtisanGoods",
                "OBJECT_CATEGORY":-26,
                "OBJECT_PRICE":192,
                "EDIBILITY":20,
                "DRINKABILITY":false,
                "ITEM_SPRITE":835,
                 //hybrid tokens
                "RECIPE_ACQUISITION":"default",
                "RECIPE_YIELD": 1,
                "ING1":"192",
                "ING1_COUNT":"2",
                "ING2":"",
                "ING2_COUNT":"",
                "ING3":"",
                "ING3_COUNT":"",
                "ING4":"",
                "ING4_COUNT":"",
                "ING5":"",
                "ING5_COUNT":"",
            }
        },
        {
            "LogName": "Object Data Tokens - Whiskey",
            "Action": "Include",
            "FromFile": "Data/Templates/Objects.json, Data/Templates/{{Method}}.json",
            "LocalTokens": {
                "MACHINE_TYPE": "{{ModId}}_SyrupMaker",
                "ITEM_TYPE": "Alcohol",
                "ITEM_FLAVOR":"Whiskey",
                "INPUT1":"id_(O)270",
                "INPUT1_COUNT":2,
                "INPUT2":"",
                "PRICE_MULTIPLIER": 1.2,
                "PRICE_ADDER": 0,
                "MINUTES_UNTIL_READY": 20,
                "OBJECT_TYPE":"ArtisanGoods",
                "OBJECT_CATEGORY":-26,
                "OBJECT_PRICE":120,
                "EDIBILITY":20,
                "DRINKABILITY":false,
                "ITEM_SPRITE":836,
                 //hybrid tokens
                "RECIPE_ACQUISITION":"default",
                "RECIPE_YIELD": 1,
                "ING1":"270",
                "ING1_COUNT":"2",
                "ING2":"",
                "ING2_COUNT":"",
                "ING3":"",
                "ING3_COUNT":"",
                "ING4":"",
                "ING4_COUNT":"",
                "ING5":"",
                "ING5_COUNT":"",
            }
        },
        {
            "LogName": "Object Data Tokens - Aromatic Bitters",
            "Action": "Include",
            "FromFile": "Data/Templates/Objects.json, Data/Templates/{{Method}}.json",
            "LocalTokens": {
                "MACHINE_TYPE": "{{ModId}}_SyrupMaker",
                "ITEM_TYPE": "Bitters",
                "ITEM_FLAVOR":"Aromatic",
                "INPUT1":"id_(O){{ModId}}_Wormwood",
                "INPUT1_COUNT":1,
                "INPUT2":"",
                "PRICE_MULTIPLIER": 1.2,
                "PRICE_ADDER": 0,
                "MINUTES_UNTIL_READY": 20,
                "OBJECT_TYPE":"ArtisanGoods",
                "OBJECT_CATEGORY":-26,
                "OBJECT_PRICE":57,
                "EDIBILITY":20,
                "DRINKABILITY":false,
                "ITEM_SPRITE":826,
                 //hybrid tokens
                "RECIPE_ACQUISITION":"default",
                "RECIPE_YIELD": 5,
                "ING1":"{{ModId}}_Wormwood",
                "ING1_COUNT": 1,
                "ING2":"{{ModId}}_Cinnamon",
                "ING2_COUNT": 1,
                "ING3":"{{ModId}}_Thyme",
                "ING3_COUNT": 1,
                "ING4":"{{ModId}}_Rosemary",
                "ING4_COUNT": 1,
                "ING5":"",
                "ING5_COUNT":"",
            }
        },
         {
            "LogName": "Object Data Tokens - Citrus Bitters",
            "Action": "Include",
            "FromFile": "Data/Templates/Objects.json, Data/Templates/{{Method}}.json",
            "LocalTokens": {
                "MACHINE_TYPE": "{{ModId}}_SyrupMaker",
                "ITEM_TYPE": "Bitters",
                "ITEM_FLAVOR":"Citrus",
                "INPUT1":"id_(O){{ModId}}_Lemon",
                "INPUT1_COUNT":1,
                "INPUT2":"",
                "PRICE_MULTIPLIER": 1.2,
                "PRICE_ADDER": 0,
                "MINUTES_UNTIL_READY": 20,
                "OBJECT_TYPE":"ArtisanGoods",
                "OBJECT_CATEGORY":-26,
                "OBJECT_PRICE":80,
                "EDIBILITY":20,
                "DRINKABILITY":false,
                "ITEM_SPRITE":828,
                 //hybrid tokens
                "RECIPE_ACQUISITION":"default",
                "RECIPE_YIELD": 5,
                "ING1":"{{ModId}}_Lemon",
                "ING1_COUNT": 1,
                "ING2":"{{ModId}}_Lime",
                "ING2_COUNT": 1,
                "ING3":"{{ModId}}_Gentian_Root",
                "ING3_COUNT": 1,
                "ING4":"{{ModId}}_Basil",
                "ING4_COUNT": 1,
                "ING5":"",
                "ING5_COUNT":"",
            }
        },
         {
            "LogName": "Object Data Tokens - Floral Bitters",
            "Action": "Include",
            "FromFile": "Data/Templates/Objects.json, Data/Templates/{{Method}}.json",
            "LocalTokens": {
                "MACHINE_TYPE": "{{ModId}}_SyrupMaker",
                "ITEM_TYPE": "Bitters",
                "ITEM_FLAVOR":"Floral",
                "INPUT1":"id_(O){{ModId}}_Gentian_Root",
                "INPUT1_COUNT":1,
                "INPUT2":"",
                "PRICE_MULTIPLIER": 1.2,
                "PRICE_ADDER": 0,
                "MINUTES_UNTIL_READY": 20,
                "OBJECT_TYPE":"ArtisanGoods",
                "OBJECT_CATEGORY":-26,
                "OBJECT_PRICE":88,
                "EDIBILITY":20,
                "DRINKABILITY":false,
                "ITEM_SPRITE":829,
                 //hybrid tokens
                "RECIPE_ACQUISITION":"default",
                "RECIPE_YIELD": 5,
                "ING1":"{{ModId}}_Gentian_Root",
                "ING1_COUNT": 1,
                "ING2":"{{ModId}}_Lavender",
                "ING2_COUNT": 1,
                "ING3":"{{ModId}}_Chamomile",
                "ING3_COUNT": 1,
                "ING4":"{{ModId}}_Mint",
                "ING4_COUNT": 1,
                "ING5":"",
                "ING5_COUNT":"",
            }
        },
        {
            "LogName": "Object Data Tokens - Pixie Bitters",
            "Action": "Include",
            "FromFile": "Data/Templates/Objects.json, Data/Templates/{{Method}}.json",
            "LocalTokens": {
                "MACHINE_TYPE": "{{ModId}}_SyrupMaker",
                "ITEM_TYPE": "Bitters",
                "ITEM_FLAVOR":"Pixie",
                "INPUT1":"id_(O){{ModId}}_Gentian_Root",
                "INPUT1_COUNT":1,
                "INPUT2":"",
                "PRICE_MULTIPLIER": 1.2,
                "PRICE_ADDER": 0,
                "MINUTES_UNTIL_READY": 20,
                "OBJECT_TYPE":"ArtisanGoods",
                "OBJECT_CATEGORY":-26,
                "OBJECT_PRICE":100,
                "EDIBILITY":20,
                "DRINKABILITY":false,
                "ITEM_SPRITE":831,
                 //hybrid tokens
                "RECIPE_ACQUISITION":"default",
                "RECIPE_YIELD": 5,
                "ING1":"{{ModId}}_Gentian_Root",
                "ING1_COUNT": 1,
                "ING2":"22",
                "ING2_COUNT": 1,
                "ING3":"595",
                "ING3_COUNT": 1,
                "ING4":"{{ModId}}_Basil",
                "ING4_COUNT": 1,
                "ING5":"",
                "ING5_COUNT":"",
            }
        },
        {
            "LogName": "Object Data Tokens - Star Bitters",
            "Action": "Include",
            "FromFile": "Data/Templates/Objects.json, Data/Templates/{{Method}}.json",
            "LocalTokens": {
                "MACHINE_TYPE": "{{ModId}}_SyrupMaker",
                "ITEM_TYPE": "Bitters",
                "ITEM_FLAVOR":"Star",
                "INPUT1":"id_(O){{ModId}}_Wormwood",
                "INPUT1_COUNT":1,
                "INPUT2":"",
                "PRICE_MULTIPLIER": 1.2,
                "PRICE_ADDER": 0,
                "MINUTES_UNTIL_READY": 20,
                "OBJECT_TYPE":"ArtisanGoods",
                "OBJECT_CATEGORY":-26,
                "OBJECT_PRICE":215,
                "EDIBILITY":20,
                "DRINKABILITY":false,
                "ITEM_SPRITE":833,
                 //hybrid tokens
                "RECIPE_ACQUISITION":"default",
                "RECIPE_YIELD": 5,
                "ING1":"{{ModId}}_Wormwood",
                "ING1_COUNT": 1,
                "ING2":"{{ModId}}_Sage",
                "ING2_COUNT": 1,
                "ING3":"268",
                "ING3_COUNT": 1,
                "ING4":"396",
                "ING4_COUNT": 1,
                "ING5":"",
                "ING5_COUNT":"",
            }
        },

//flower waters

        {
            "LogName": "Object Data Tokens - Rose Water",
            "Action": "Include",
            "FromFile": "Data/Templates/Objects.json, Data/Templates/{{Method}}.json",
            "LocalTokens": {
                "MACHINE_TYPE": "{{ModId}}_KitchenBlender",
                "ITEM_TYPE": "Water",
                "ITEM_FLAVOR":"Rose",
                "INPUT1":"id_(O)595",
                "INPUT1_COUNT":2,
                "INPUT2":"",
                "PRICE_MULTIPLIER": 1.2,
                "PRICE_ADDER": 0,
                "MINUTES_UNTIL_READY": 20,
                "OBJECT_TYPE":"ArtisanGoods",
                "OBJECT_CATEGORY":-26,
                "OBJECT_PRICE":696,
                "EDIBILITY":20,
                "DRINKABILITY":false,
                "ITEM_SPRITE":847,
                 //hybrid tokens
                "RECIPE_ACQUISITION":"default",
                "RECIPE_YIELD": 1,
                "ING1":"595",
                "ING1_COUNT":"2",
                "ING2":"",
                "ING2_COUNT":"",
                "ING3":"",
                "ING3_COUNT":"",
                "ING4":"",
                "ING4_COUNT":"",
                "ING5":"",
                "ING5_COUNT":"",
            }
        },

        {
            "LogName": "Object Data Tokens - Hibiscus Water",
            "Action": "Include",
            "FromFile": "Data/Templates/Objects.json, Data/Templates/{{Method}}.json",
            "LocalTokens": {
                "MACHINE_TYPE": "{{ModId}}_KitchenBlender",
                "ITEM_TYPE": "Water",
                "ITEM_FLAVOR":"Hibiscus",
                "INPUT1":"id_(O){{ModId}}_Hibiscus",
                "INPUT1_COUNT":2,
                "INPUT2":"",
                "PRICE_MULTIPLIER": 1.2,
                "PRICE_ADDER": 0,
                "MINUTES_UNTIL_READY": 20,
                "OBJECT_TYPE":"ArtisanGoods",
                "OBJECT_CATEGORY":-26,
                "OBJECT_PRICE":288,
                "EDIBILITY":20,
                "DRINKABILITY":false,
                "ITEM_SPRITE":893,
                 //hybrid tokens
                "RECIPE_ACQUISITION":"default",
                "RECIPE_YIELD": 1,
                "ING1":"{{ModId}}_Hibiscus",
                "ING1_COUNT":"2",
                "ING2":"",
                "ING2_COUNT":"",
                "ING3":"",
                "ING3_COUNT":"",
                "ING4":"",
                "ING4_COUNT":"",
                "ING5":"",
                "ING5_COUNT":"",
            }
        },
        {
            "LogName": "Object Data Tokens - Jasmine Water",
            "Action": "Include",
            "FromFile": "Data/Templates/Objects.json, Data/Templates/{{Method}}.json",
            "LocalTokens": {
                "MACHINE_TYPE": "{{ModId}}_KitchenBlender",
                "ITEM_TYPE": "Water",
                "ITEM_FLAVOR":"Jasmine",
                "INPUT1":"id_(O){{ModId}}_Jasmine",
                "INPUT1_COUNT":2,
                "INPUT2":"",
                "PRICE_MULTIPLIER": 1.2,
                "PRICE_ADDER": 0,
                "MINUTES_UNTIL_READY": 20,
                "OBJECT_TYPE":"ArtisanGoods",
                "OBJECT_CATEGORY":-26,
                "OBJECT_PRICE":168,
                "EDIBILITY":20,
                "DRINKABILITY":false,
                "ITEM_SPRITE":894,
                 //hybrid tokens
                "RECIPE_ACQUISITION":"default",
                "RECIPE_YIELD": 1,
                "ING1":"{{ModId}}_Jasmine",
                "ING1_COUNT":"2",
                "ING2":"",
                "ING2_COUNT":"",
                "ING3":"",
                "ING3_COUNT":"",
                "ING4":"",
                "ING4_COUNT":"",
                "ING5":"",
                "ING5_COUNT":"",
            }
        },
        {
            "LogName": "Object Data Tokens - Elderflower Water",
            "Action": "Include",
            "FromFile": "Data/Templates/Objects.json, Data/Templates/{{Method}}.json",
            "LocalTokens": {
                "MACHINE_TYPE": "{{ModId}}_KitchenBlender",
                "ITEM_TYPE": "Water",
                "ITEM_FLAVOR":"Elderflower",
                "INPUT1":"id_(O){{ModId}}_Elderberries",
                "INPUT1_COUNT":2,
                "INPUT2":"",
                "PRICE_MULTIPLIER": 1.2,
                "PRICE_ADDER": 0,
                "MINUTES_UNTIL_READY": 20,
                "OBJECT_TYPE":"ArtisanGoods",
                "OBJECT_CATEGORY":-26,
                "OBJECT_PRICE":408,
                "EDIBILITY":20,
                "DRINKABILITY":false,
                "ITEM_SPRITE":895,
                 //hybrid tokens
                "RECIPE_ACQUISITION":"default",
                "RECIPE_YIELD": 1,
                "ING1":"{{ModId}}_Elderberries",
                "ING1_COUNT":"2",
                "ING2":"",
                "ING2_COUNT":"",
                "ING3":"",
                "ING3_COUNT":"",
                "ING4":"",
                "ING4_COUNT":"",
                "ING5":"",
                "ING5_COUNT":"",
            }
        },
        {
            "LogName": "Object Data Tokens - Lavender Flower Water",
            "Action": "Include",
            "FromFile": "Data/Templates/Objects.json, Data/Templates/{{Method}}.json",
            "LocalTokens": {
                "MACHINE_TYPE": "{{ModId}}_KitchenBlender",
                "ITEM_TYPE": "Water",
                "ITEM_FLAVOR":"Lavender",
                "INPUT1":"id_(O){{ModId}}_Lavender",
                "INPUT1_COUNT":2,
                "INPUT2":"",
                "PRICE_MULTIPLIER": 1.2,
                "PRICE_ADDER": 0,
                "MINUTES_UNTIL_READY": 20,
                "OBJECT_TYPE":"ArtisanGoods",
                "OBJECT_CATEGORY":-26,
                "OBJECT_PRICE":204,
                "EDIBILITY":20,
                "DRINKABILITY":false,
                "ITEM_SPRITE":907,
                 //hybrid tokens
                "RECIPE_ACQUISITION":"default",
                "RECIPE_YIELD": 1,
                "ING1":"832",
                "ING1_COUNT":"2",
                "ING2":"",
                "ING2_COUNT":"",
                "ING3":"",
                "ING3_COUNT":"",
                "ING4":"",
                "ING4_COUNT":"",
                "ING5":"",
                "ING5_COUNT":"",
            }
        },

        {
            "LogName": "Object Data Tokens - Blue Jazz Flower Water",
            "Action": "Include",
            "FromFile": "Data/Templates/Objects.json, Data/Templates/{{Method}}.json",
            "LocalTokens": {
                "MACHINE_TYPE": "{{ModId}}_KitchenBlender",
                "ITEM_TYPE": "Water",
                "ITEM_FLAVOR":"Blue_Jazz",
                "INPUT1":"id_(O)597",
                "INPUT1_COUNT":2,
                "INPUT2":"",
                "PRICE_MULTIPLIER": 1.2,
                "PRICE_ADDER": 0,
                "MINUTES_UNTIL_READY": 20,
                "OBJECT_TYPE":"ArtisanGoods",
                "OBJECT_CATEGORY":-26,
                "OBJECT_PRICE":120,
                "EDIBILITY":20,
                "DRINKABILITY":false,
                "ITEM_SPRITE":908,
                 //hybrid tokens
                "RECIPE_ACQUISITION":"default",
                "RECIPE_YIELD": 1,
                "ING1":"597",
                "ING1_COUNT":"2",
                "ING2":"",
                "ING2_COUNT":"",
                "ING3":"",
                "ING3_COUNT":"",
                "ING4":"",
                "ING4_COUNT":"",
                "ING5":"",
                "ING5_COUNT":"",
            }
        },
        {
            "LogName": "Object Data Tokens - Tulip Flower Water",
            "Action": "Include",
            "FromFile": "Data/Templates/Objects.json, Data/Templates/{{Method}}.json",
            "LocalTokens": {
                "MACHINE_TYPE": "{{ModId}}_KitchenBlender",
                "ITEM_TYPE": "Water",
                "ITEM_FLAVOR":"Tulip",
                "INPUT1":"id_(O)591",
                "INPUT1_COUNT":2,
                "INPUT2":"",
                "PRICE_MULTIPLIER": 1.2,
                "PRICE_ADDER": 0,
                "MINUTES_UNTIL_READY": 20,
                "OBJECT_TYPE":"ArtisanGoods",
                "OBJECT_CATEGORY":-26,
                "OBJECT_PRICE":72,
                "EDIBILITY":20,
                "DRINKABILITY":false,
                "ITEM_SPRITE":909,
                 //hybrid tokens
                "RECIPE_ACQUISITION":"default",
                "RECIPE_YIELD": 1,
                "ING1":"591",
                "ING1_COUNT":"2",
                "ING2":"",
                "ING2_COUNT":"",
                "ING3":"",
                "ING3_COUNT":"",
                "ING4":"",
                "ING4_COUNT":"",
                "ING5":"",
                "ING5_COUNT":"",
            }
        },

        {
            "LogName": "Object Data Tokens - Spangle Flower Water",
            "Action": "Include",
            "FromFile": "Data/Templates/Objects.json, Data/Templates/{{Method}}.json",
            "LocalTokens": {
                "MACHINE_TYPE": "{{ModId}}_KitchenBlender",
                "ITEM_TYPE": "Water",
                "ITEM_FLAVOR":"Spangle",
                "INPUT1":"id_(O)593",
                "INPUT1_COUNT":2,
                "INPUT2":"",
                "PRICE_MULTIPLIER": 1.2,
                "PRICE_ADDER": 0,
                "MINUTES_UNTIL_READY": 20,
                "OBJECT_TYPE":"ArtisanGoods",
                "OBJECT_CATEGORY":-26,
                "OBJECT_PRICE":216,
                "EDIBILITY":20,
                "DRINKABILITY":false,
                "ITEM_SPRITE":910,
                 //hybrid tokens
                "RECIPE_ACQUISITION":"default",
                "RECIPE_YIELD": 1,
                "ING1":"593",
                "ING1_COUNT":"2",
                "ING2":"",
                "ING2_COUNT":"",
                "ING3":"",
                "ING3_COUNT":"",
                "ING4":"",
                "ING4_COUNT":"",
                "ING5":"",
                "ING5_COUNT":"",
            }
        },
        {
            "LogName": "Object Data Tokens - Peony Flower Water",
            "Action": "Include",
            "FromFile": "Data/Templates/Objects.json, Data/Templates/{{Method}}.json",
            "LocalTokens": {
                "MACHINE_TYPE": "{{ModId}}_KitchenBlender",
                "ITEM_TYPE": "Water",
                "ITEM_FLAVOR":"Peony",
                "INPUT1":"id_(O){{ModId}}_Peony",
                "INPUT1_COUNT":2,
                "INPUT2":"",
                "PRICE_MULTIPLIER": 1.2,
                "PRICE_ADDER": 0,
                "MINUTES_UNTIL_READY": 20,
                "OBJECT_TYPE":"ArtisanGoods",
                "OBJECT_CATEGORY":-26,
                "OBJECT_PRICE":372,
                "EDIBILITY":20,
                "DRINKABILITY":false,
                "ITEM_SPRITE":911,
                 //hybrid tokens
                "RECIPE_ACQUISITION":"default",
                "RECIPE_YIELD": 1,
                "ING1":"{{ModId}}_Peony",
                "ING1_COUNT":"2",
                "ING2":"",
                "ING2_COUNT":"",
                "ING3":"",
                "ING3_COUNT":"",
                "ING4":"",
                "ING4_COUNT":"",
                "ING5":"",
                "ING5_COUNT":"",
            }
        },







    ]
}