{
    "Changes": [
        
/////////////////
// ALE OBJECTS //
/////////////////

        {
            "LogName":"Add Base Ale Objects",
            "Action": "EditData",
            "Target": "Data/Objects",
            "Entries": {
                "wildflour.alesxmeads_FruitAle": {
                    "Name": "wildflour.alesxmeads_FruitAle",
                    "DisplayName": "{{i18n:alesxmeads_FruitAle.name}}",
                    "Description": "{{i18n:alesxmeads_FruitAle.description}}",
                    "Type": "ArtisanGoods",          
                    "Category": -26,
                    "Edibility": 20,
                    "Price": 100,
                    "ExcludeFromShippingCollection": true,
                    "ContextTags":
                    ["wildflour_ale_item",
                    "alcohol_item",
                    "color_gold"],

                    "Texture": "Mods/wildflour.alesxmeads/Objects",
                    "SpriteIndex": 22
            },
                "wildflour.alesxmeads_FruitMead": {
                    "Name": "wildflour.alesxmeads_FruitMead",
                    "DisplayName": "{{i18n:alesxmeads_FruitMead.name}}",
                    "Description": "{{i18n:alesxmeads_FruitMead.description}}",
                    "Type": "ArtisanGoods",          
                    "Category": -26,
                    "Edibility": 20,
                    "Price": 100,
                    "ExcludeFromShippingCollection": true,
                    "ContextTags":
                    ["wildflour_mead_item",
                    "alcohol_item",
                    "color_gold"],

                    "Texture": "Mods/wildflour.alesxmeads/Objects",
                    "SpriteIndex": 104
            },
                "wildflour.alesxmeads_FlowerMead": {
                    "Name": "wildflour.alesxmeads_FlowerMead",
                    "DisplayName": "{{i18n:alesxmeads_FlowerMead.name}}",
                    "Description": "{{i18n:alesxmeads_FlowerMead.description}}",
                    "Type": "ArtisanGoods",          
                    "Category": -26,
                    "Edibility": 20,
                    "Price": 100,
                    "ExcludeFromShippingCollection": true,
                    "ContextTags":
                    ["wildflour_mead_item",
                    "alcohol_item",
                    "color_gold"],

                    "Texture": "Mods/wildflour.alesxmeads/Objects",
                    "SpriteIndex": 104
            },
                "wildflour.alesxmeads_ancient_ale": {
                    "Name": "wildflour.alesxmeads_ancient_ale",
                    "DisplayName": "{{i18n:alesxmeads_ancient_ale.name}}",
                    "Description": "{{i18n:alesxmeads_ancient_ale.description}}",
                    "Type": "ArtisanGoods",          
                    "Category": -26,
                    "Edibility": 20,
                    "Price": 100,
                    "ExcludeFromShippingCollection": "{{ShippingConfig}}",
                    "ContextTags":
                    ["wildflour_ale_item",
                    "alcohol_item",
                    "color_cyan"],

                    "Texture": "Mods/wildflour.alesxmeads/Objects",
                    "SpriteIndex": 0
            },
                "wildflour.alesxmeads_apple_ale": {
                    "Name": "wildflour.alesxmeads_apple_ale",
                    "DisplayName": "{{i18n:alesxmeads_apple_ale.name}}",
                    "Description": "{{i18n:alesxmeads_apple_ale.description}}",
                    "Type": "ArtisanGoods",          
                    "Category": -26,
                    "Edibility": 20,
                    "Price": 100,
                    "ExcludeFromShippingCollection": "{{ShippingConfig}}",
                    "ContextTags":
                    ["wildflour_ale_item",
                    "alcohol_item",
                    "color_red"],

                    "Texture": "Mods/wildflour.alesxmeads/Objects",
                    "SpriteIndex": 1
            },
                "wildflour.alesxmeads_apricot_ale": {
                    "Name": "wildflour.alesxmeads_apricot_ale",
                    "DisplayName": "{{i18n:alesxmeads_apricot_ale.name}}",
                    "Description": "{{i18n:alesxmeads_apricot_ale.description}}",
                    "Type": "ArtisanGoods",          
                    "Category": -26,
                    "Edibility": 20,
                    "Price": 100,
                    "ExcludeFromShippingCollection": "{{ShippingConfig}}",
                    "ContextTags":
                    ["wildflour_ale_item",
                    "alcohol_item",
                    "color_light_orange"],

                    "Texture": "Mods/wildflour.alesxmeads/Objects",
                    "SpriteIndex": 2
            },
                "wildflour.alesxmeads_banana_ale": {
                    "Name": "wildflour.alesxmeads_banana_ale",
                    "DisplayName": "{{i18n:alesxmeads_banana_ale.name}}",
                    "Description": "{{i18n:alesxmeads_banana_ale.description}}",
                    "Type": "ArtisanGoods",          
                    "Category": -26,
                    "Edibility": 20,
                    "Price": 100,
                    "ExcludeFromShippingCollection": "{{ShippingConfig}}",
                    "ContextTags":
                    ["wildflour_ale_item",
                    "alcohol_item",
                    "color_yellow"],

                    "Texture": "Mods/wildflour.alesxmeads/Objects",
                    "SpriteIndex": 3
            },
                "wildflour.alesxmeads_blackberry_ale": {
                    "Name": "wildflour.alesxmeads_blackberry_ale",
                    "DisplayName": "{{i18n:alesxmeads_blackberry_ale.name}}",
                    "Description": "{{i18n:alesxmeads_blackberry_ale.description}}",
                    "Type": "ArtisanGoods",          
                    "Category": -26,
                    "Edibility": 20,
                    "Price": 100,
                    "ExcludeFromShippingCollection": "{{ShippingConfig}}",
                    "ContextTags":
                    ["wildflour_ale_item",
                    "alcohol_item",
                    "color_dark_blue"],

                    "Texture": "Mods/wildflour.alesxmeads/Objects",
                    "SpriteIndex": 4
            },
                "wildflour.alesxmeads_blueberry_ale": {
                    "Name": "wildflour.alesxmeads_blueberry_ale",
                    "DisplayName": "{{i18n:alesxmeads_blueberry_ale.name}}",
                    "Description": "{{i18n:alesxmeads_blueberry_ale.description}}",
                    "Type": "ArtisanGoods",          
                    "Category": -26,
                    "Edibility": 20,
                    "Price": 100,
                    "ExcludeFromShippingCollection": "{{ShippingConfig}}",
                    "ContextTags":
                    ["wildflour_ale_item",
                    "alcohol_item",
                    "color_blue"],

                    "Texture": "Mods/wildflour.alesxmeads/Objects",
                    "SpriteIndex": 5
            },
                "wildflour.alesxmeads_cactus_ale": {
                    "Name": "wildflour.alesxmeads_cactus_ale",
                    "DisplayName": "{{i18n:alesxmeads_cactus_ale.name}}",
                    "Description": "{{i18n:alesxmeads_cactus_ale.description}}",
                    "Type": "ArtisanGoods",          
                    "Category": -26,
                    "Edibility": 20,
                    "Price": 100,
                    "ExcludeFromShippingCollection": "{{ShippingConfig}}",
                    "ContextTags":
                    ["wildflour_ale_item",
                    "alcohol_item",
                    "color_white"],

                    "Texture": "Mods/wildflour.alesxmeads/Objects",
                    "SpriteIndex": 6
            },
                "wildflour.alesxmeads_cherry_ale": {
                    "Name": "wildflour.alesxmeads_cherry_ale",
                    "DisplayName": "{{i18n:alesxmeads_cherry_ale.name}}",
                    "Description": "{{i18n:alesxmeads_cherry_ale.description}}",
                    "Type": "ArtisanGoods",          
                    "Category": -26,
                    "Edibility": 20,
                    "Price": 100,
                    "ExcludeFromShippingCollection": "{{ShippingConfig}}",
                    "ContextTags":
                    ["wildflour_ale_item",
                    "alcohol_item",
                    "color_red"],

                    "Texture": "Mods/wildflour.alesxmeads/Objects",
                    "SpriteIndex": 7
            },
                "wildflour.alesxmeads_coconut_ale": {
                    "Name": "wildflour.alesxmeads_coconut_ale",
                    "DisplayName": "{{i18n:alesxmeads_coconut_ale.name}}",
                    "Description": "{{i18n:alesxmeads_coconut_ale.description}}",
                    "Type": "ArtisanGoods",          
                    "Category": -26,
                    "Edibility": 20,
                    "Price": 100,
                    "ExcludeFromShippingCollection": "{{ShippingConfig}}",
                    "ContextTags":
                    ["wildflour_ale_item",
                    "alcohol_item",
                    "color_sand"],

                    "Texture": "Mods/wildflour.alesxmeads/Objects",
                    "SpriteIndex": 8
            },
                "wildflour.alesxmeads_cranberry_ale": {
                    "Name": "wildflour.alesxmeads_cranberry_ale",
                    "DisplayName": "{{i18n:alesxmeads_cranberry_ale.name}}",
                    "Description": "{{i18n:alesxmeads_cranberry_ale.description}}",
                    "Type": "ArtisanGoods",          
                    "Category": -26,
                    "Edibility": 20,
                    "Price": 100,
                    "ExcludeFromShippingCollection": "{{ShippingConfig}}",
                    "ContextTags":
                    ["wildflour_ale_item",
                    "alcohol_item",
                    "color_dark_red"],

                    "Texture": "Mods/wildflour.alesxmeads/Objects",
                    "SpriteIndex": 9
            },
                "wildflour.alesxmeads_crystal_ale": {
                    "Name": "wildflour.alesxmeads_crystal_ale",
                    "DisplayName": "{{i18n:alesxmeads_crystal_ale.name}}",
                    "Description": "{{i18n:alesxmeads_crystal_ale.description}}",
                    "Type": "ArtisanGoods",          
                    "Category": -26,
                    "Edibility": 20,
                    "Price": 100,
                    "ExcludeFromShippingCollection": "{{ShippingConfig}}",
                    "ContextTags":
                    ["wildflour_ale_item",
                    "alcohol_item",
                    "color_cyan"],

                    "Texture": "Mods/wildflour.alesxmeads/Objects",
                    "SpriteIndex": 10
            },
                "wildflour.alesxmeads_gem_ale": {
                    "Name": "wildflour.alesxmeads_gem_ale",
                    "DisplayName": "{{i18n:alesxmeads_gem_ale.name}}",
                    "Description": "{{i18n:alesxmeads_gem_ale.description}}",
                    "Type": "ArtisanGoods",          
                    "Category": -26,
                    "Edibility": 20,
                    "Price": 100,
                    "ExcludeFromShippingCollection": "{{ShippingConfig}}",
                    "ContextTags":
                    ["wildflour_ale_item",
                    "alcohol_item",
                    "color_dark_pink"],

                    "Texture": "Mods/wildflour.alesxmeads/Objects",
                    "SpriteIndex": 11
            },
                "wildflour.alesxmeads_mango_ale": {
                    "Name": "wildflour.alesxmeads_mango_ale",
                    "DisplayName": "{{i18n:alesxmeads_mango_ale.name}}",
                    "Description": "{{i18n:alesxmeads_mango_ale.description}}",
                    "Type": "ArtisanGoods",          
                    "Category": -26,
                    "Edibility": 20,
                    "Price": 100,
                    "ExcludeFromShippingCollection": "{{ShippingConfig}}",
                    "ContextTags":
                    ["wildflour_ale_item",
                    "alcohol_item",
                    "color_orange"],

                    "Texture": "Mods/wildflour.alesxmeads/Objects",
                    "SpriteIndex": 12
            },
                "wildflour.alesxmeads_melon_ale": {
                    "Name": "wildflour.alesxmeads_melon_ale",
                    "DisplayName": "{{i18n:alesxmeads_melon_ale.name}}",
                    "Description": "{{i18n:alesxmeads_melon_ale.description}}",
                    "Type": "ArtisanGoods",          
                    "Category": -26,
                    "Edibility": 20,
                    "Price": 100,
                    "ExcludeFromShippingCollection": "{{ShippingConfig}}",
                    "ContextTags":
                    ["wildflour_ale_item",
                    "alcohol_item",
                    "color_pink"],

                    "Texture": "Mods/wildflour.alesxmeads/Objects",
                    "SpriteIndex": 13
            },
                "wildflour.alesxmeads_orange_ale": {
                    "Name": "wildflour.alesxmeads_orange_ale",
                    "DisplayName": "{{i18n:alesxmeads_orange_ale.name}}",
                    "Description": "{{i18n:alesxmeads_orange_ale.description}}",
                    "Type": "ArtisanGoods",          
                    "Category": -26,
                    "Edibility": 20,
                    "Price": 100,
                    "ExcludeFromShippingCollection": "{{ShippingConfig}}",
                    "ContextTags":
                    ["wildflour_ale_item",
                    "alcohol_item",
                    "color_orange"],

                    "Texture": "Mods/wildflour.alesxmeads/Objects",
                    "SpriteIndex": 14
            },
                "wildflour.alesxmeads_peach_ale": {
                    "Name": "wildflour.alesxmeads_peach_ale",
                    "DisplayName": "{{i18n:alesxmeads_peach_ale.name}}",
                    "Description": "{{i18n:alesxmeads_peach_ale.description}}",
                    "Type": "ArtisanGoods",          
                    "Category": -26,
                    "Edibility": 20,
                    "Price": 100,
                    "ExcludeFromShippingCollection": "{{ShippingConfig}}",
                    "ContextTags":
                    ["wildflour_ale_item",
                    "alcohol_item",
                    "color_pink"],

                    "Texture": "Mods/wildflour.alesxmeads/Objects",
                    "SpriteIndex": 15
            },
                "wildflour.alesxmeads_pineapple_ale": {
                    "Name": "wildflour.alesxmeads_pineapple_ale",
                    "DisplayName": "{{i18n:alesxmeads_pineapple_ale.name}}",
                    "Description": "{{i18n:alesxmeads_pineapple_ale.description}}",
                    "Type": "ArtisanGoods",          
                    "Category": -26,
                    "Edibility": 20,
                    "Price": 100,
                    "ExcludeFromShippingCollection": "{{ShippingConfig}}",
                    "ContextTags":
                    ["wildflour_ale_item",
                    "alcohol_item",
                    "color_gold"],

                    "Texture": "Mods/wildflour.alesxmeads/Objects",
                    "SpriteIndex": 12
            },
                "wildflour.alesxmeads_plum_ale": {
                    "Name": "wildflour.alesxmeads_plum_ale",
                    "DisplayName": "{{i18n:alesxmeads_plum_ale.name}}",
                    "Description": "{{i18n:alesxmeads_plum_ale.description}}",
                    "Type": "ArtisanGoods",          
                    "Category": -26,
                    "Edibility": 20,
                    "Price": 100,
                    "ExcludeFromShippingCollection": "{{ShippingConfig}}",
                    "ContextTags":
                    ["wildflour_ale_item",
                    "alcohol_item",
                    "color_dark_red"],

                    "Texture": "Mods/wildflour.alesxmeads/Objects",
                    "SpriteIndex": 16
            },
                "wildflour.alesxmeads_pomegranate_ale": {
                    "Name": "wildflour.alesxmeads_pomegranate_ale",
                    "DisplayName": "{{i18n:alesxmeads_pomegranate_ale.name}}",
                    "Description": "{{i18n:alesxmeads_pomegranate_ale.description}}",
                    "Type": "ArtisanGoods",          
                    "Category": -26,
                    "Edibility": 20,
                    "Price": 100,
                    "ExcludeFromShippingCollection": "{{ShippingConfig}}",
                    "ContextTags":
                    ["wildflour_ale_item",
                    "alcohol_item",
                    "color_dark_red"],

                    "Texture": "Mods/wildflour.alesxmeads/Objects",
                    "SpriteIndex": 17
            },
                "wildflour.alesxmeads_pumpkin_ale": {
                    "Name": "wildflour.alesxmeads_pumpkin_ale",
                    "DisplayName": "{{i18n:alesxmeads_pumpkin_ale.name}}",
                    "Description": "{{i18n:alesxmeads_pumpkin_ale.description}}",
                    "Type": "ArtisanGoods",          
                    "Category": -26,
                    "Edibility": 20,
                    "Price": 100,
                    "ExcludeFromShippingCollection": "{{ShippingConfig}}",
                    "ContextTags":
                    ["wildflour_ale_item",
                    "alcohol_item",
                    "color_dark_orange"],

                    "Texture": "Mods/wildflour.alesxmeads/Objects",
                    "SpriteIndex": 18
            },
                "wildflour.alesxmeads_spiced_ale": {
                    "Name": "wildflour.alesxmeads_spiced_ale",
                    "DisplayName": "{{i18n:alesxmeads_spiced_ale.name}}",
                    "Description": "{{i18n:alesxmeads_spiced_ale.description}}",
                    "Type": "ArtisanGoods",          
                    "Category": -26,
                    "Edibility": 20,
                    "Price": 100,
                    "ExcludeFromShippingCollection": "{{ShippingConfig}}",
                    "ContextTags":
                    ["wildflour_ale_item",
                    "alcohol_item",
                    "color_dark_red"],

                    "Texture": "Mods/wildflour.alesxmeads/Objects",
                    "SpriteIndex": 19
            },
                "wildflour.alesxmeads_starfruit_ale": {
                    "Name": "wildflour.alesxmeads_starfruit_ale",
                    "DisplayName": "{{i18n:alesxmeads_starfruit_ale.name}}",
                    "Description": "{{i18n:alesxmeads_starfruit_ale.description}}",
                    "Type": "ArtisanGoods",          
                    "Category": -26,
                    "Edibility": 20,
                    "Price": 100,
                    "ExcludeFromShippingCollection": "{{ShippingConfig}}",
                    "ContextTags":
                    ["wildflour_ale_item",
                    "alcohol_item",
                    "color_yellow"],

                    "Texture": "Mods/wildflour.alesxmeads/Objects",
                    "SpriteIndex": 20
            },
                "wildflour.alesxmeads_strawberry_ale": {
                    "Name": "wildflour.alesxmeads_strawberry_ale",
                    "DisplayName": "{{i18n:alesxmeads_strawberry_ale.name}}",
                    "Description": "{{i18n:alesxmeads_strawberry_ale.description}}",
                    "Type": "ArtisanGoods",          
                    "Category": -26,
                    "Edibility": 20,
                    "Price": 100,
                    "ExcludeFromShippingCollection": "{{ShippingConfig}}",
                    "ContextTags":
                    ["wildflour_ale_item",
                    "alcohol_item",
                    "color_pink"],

                    "Texture": "Mods/wildflour.alesxmeads/Objects",
                    "SpriteIndex": 21
            }
        }
        },


//////////////////
// MEAD OBJECTS //
//////////////////

        {
            "LogName":"Add Base Mead Objects",
            "Action":"EditData",
            "Target":"Data/Objects",
            "Entries": {
                "wildflour.alesxmeads_ancient_mead": {
                    "Name": "wildflour.alesxmeads_ancient_mead",
                    "DisplayName": "{{i18n:alesxmeads_ancient_mead.name}}",
                    "Description": "{{i18n:alesxmeads_ancient_mead.description}}",
                    "Type": "ArtisanGoods",          
                    "Category": -26,
                    "Edibility": 20,
                    "Price": 100,
                    "ExcludeFromShippingCollection": "{{ShippingConfig}}",
                    "ContextTags":
                    ["wildflour_mead_item",
                    "alcohol_item",
                    "color_cyan"],

                    "Texture": "Mods/wildflour.alesxmeads/Objects",
                    "SpriteIndex": 80
            },
                "wildflour.alesxmeads_plum_mead": {
                    "Name": "wildflour.alesxmeads_plum_mead",
                    "DisplayName": "{{i18n:alesxmeads_plum_mead.name}}",
                    "Description": "{{i18n:alesxmeads_plum_mead.description}}",
                    "Type": "ArtisanGoods",          
                    "Category": -26,
                    "Edibility": 20,
                    "Price": 100,
                    "ExcludeFromShippingCollection": "{{ShippingConfig}}",
                    "ContextTags":
                    ["wildflour_mead_item",
                    "alcohol_item",
                    "color_dark_brown"],

                    "Texture": "Mods/wildflour.alesxmeads/Objects",
                    "SpriteIndex": 81
            },
                "wildflour.alesxmeads_banana_mead": {
                    "Name": "wildflour.alesxmeads_banana_mead",
                    "DisplayName": "{{i18n:alesxmeads_banana_mead.name}}",
                    "Description": "{{i18n:alesxmeads_banana_mead.description}}",
                    "Type": "ArtisanGoods",          
                    "Category": -26,
                    "Edibility": 20,
                    "Price": 100,
                    "ExcludeFromShippingCollection": "{{ShippingConfig}}",
                    "ContextTags":
                    ["wildflour_mead_item",
                    "alcohol_item",
                    "color_dark_brown"],

                    "Texture": "Mods/wildflour.alesxmeads/Objects",
                    "SpriteIndex": 82
            },
                "wildflour.alesxmeads_pineapple_mead": {
                    "Name": "wildflour.alesxmeads_pineapple_mead",
                    "DisplayName": "{{i18n:alesxmeads_pineapple_mead.name}}",
                    "Description": "{{i18n:alesxmeads_pineapple_mead.description}}",
                    "Type": "ArtisanGoods",          
                    "Category": -26,
                    "Edibility": 20,
                    "Price": 100,
                    "ExcludeFromShippingCollection": "{{ShippingConfig}}",
                    "ContextTags":
                    ["wildflour_mead_item",
                    "alcohol_item",
                    "color_dark_brown"],

                    "Texture": "Mods/wildflour.alesxmeads/Objects",
                    "SpriteIndex": 83
            },
                "wildflour.alesxmeads_blackberry_mead": {
                    "Name": "wildflour.alesxmeads_blackberry_mead",
                    "DisplayName": "{{i18n:alesxmeads_blackberry_mead.name}}",
                    "Description": "{{i18n:alesxmeads_blackberry_mead.description}}",
                    "Type": "ArtisanGoods",          
                    "Category": -26,
                    "Edibility": 20,
                    "Price": 100,
                    "ExcludeFromShippingCollection": "{{ShippingConfig}}",
                    "ContextTags":
                    ["wildflour_mead_item",
                    "alcohol_item",
                    "color_dark_brown"],

                    "Texture": "Mods/wildflour.alesxmeads/Objects",
                    "SpriteIndex": 84
            },
                "wildflour.alesxmeads_blueberry_mead": {
                    "Name": "wildflour.alesxmeads_blueberry_mead",
                    "DisplayName": "{{i18n:alesxmeads_blueberry_mead.name}}",
                    "Description": "{{i18n:alesxmeads_blueberry_mead.description}}",
                    "Type": "ArtisanGoods",          
                    "Category": -26,
                    "Edibility": 20,
                    "Price": 100,
                    "ExcludeFromShippingCollection": "{{ShippingConfig}}",
                    "ContextTags":
                    ["wildflour_mead_item",
                    "alcohol_item",
                    "color_dark_brown"],

                    "Texture": "Mods/wildflour.alesxmeads/Objects",
                    "SpriteIndex": 85
            },
                "wildflour.alesxmeads_cactus_mead": {
                    "Name": "wildflour.alesxmeads_cactus_mead",
                    "DisplayName": "{{i18n:alesxmeads_cactus_mead.name}}",
                    "Description": "{{i18n:alesxmeads_cactus_mead.description}}",
                    "Type": "ArtisanGoods",          
                    "Category": -26,
                    "Edibility": 20,
                    "Price": 100,
                    "ExcludeFromShippingCollection": "{{ShippingConfig}}",
                    "ContextTags":
                    ["wildflour_mead_item",
                    "alcohol_item",
                    "color_dark_brown"],

                    "Texture": "Mods/wildflour.alesxmeads/Objects",
                    "SpriteIndex": 86
            },
                "wildflour.alesxmeads_apple_mead": {
                    "Name": "wildflour.alesxmeads_apple_mead",
                    "DisplayName": "{{i18n:alesxmeads_apple_mead.name}}",
                    "Description": "{{i18n:alesxmeads_apple_mead.description}}",
                    "Type": "ArtisanGoods",          
                    "Category": -26,
                    "Edibility": 20,
                    "Price": 100,
                    "ExcludeFromShippingCollection": "{{ShippingConfig}}",
                    "ContextTags":
                    ["wildflour_mead_item",
                    "alcohol_item",
                    "color_dark_brown"],

                    "Texture": "Mods/wildflour.alesxmeads/Objects",
                    "SpriteIndex": 87
            },
                "wildflour.alesxmeads_crystal_mead": {
                    "Name": "wildflour.alesxmeads_crystal_mead",
                    "DisplayName": "{{i18n:alesxmeads_crystal_mead.name}}",
                    "Description": "{{i18n:alesxmeads_crystal_mead.description}}",
                    "Type": "ArtisanGoods",          
                    "Category": -26,
                    "Edibility": 20,
                    "Price": 100,
                    "ExcludeFromShippingCollection": "{{ShippingConfig}}",
                    "ContextTags":
                    ["wildflour_mead_item",
                    "alcohol_item",
                    "color_dark_brown"],

                    "Texture": "Mods/wildflour.alesxmeads/Objects",
                    "SpriteIndex": 88
            },
                "wildflour.alesxmeads_gem_mead": {
                    "Name": "wildflour.alesxmeads_gem_mead",
                    "DisplayName": "{{i18n:alesxmeads_gem_mead.name}}",
                    "Description": "{{i18n:alesxmeads_gem_mead.description}}",
                    "Type": "ArtisanGoods",          
                    "Category": -26,
                    "Edibility": 20,
                    "Price": 100,
                    "ExcludeFromShippingCollection": "{{ShippingConfig}}",
                    "ContextTags":
                    ["wildflour_mead_item",
                    "alcohol_item",
                    "color_dark_brown"],

                    "Texture": "Mods/wildflour.alesxmeads/Objects",
                    "SpriteIndex": 89
            },
                "wildflour.alesxmeads_mango_mead": {
                    "Name": "wildflour.alesxmeads_mango_mead",
                    "DisplayName": "{{i18n:alesxmeads_mango_mead.name}}",
                    "Description": "{{i18n:alesxmeads_mango_mead.description}}",
                    "Type": "ArtisanGoods",          
                    "Category": -26,
                    "Edibility": 20,
                    "Price": 100,
                    "ExcludeFromShippingCollection": "{{ShippingConfig}}",
                    "ContextTags":
                    ["wildflour_mead_item",
                    "alcohol_item",
                    "color_dark_brown"],

                    "Texture": "Mods/wildflour.alesxmeads/Objects",
                    "SpriteIndex": 90
            },
                "wildflour.alesxmeads_orange_mead": {
                    "Name": "wildflour.alesxmeads_orange_mead",
                    "DisplayName": "{{i18n:alesxmeads_orange_mead.name}}",
                    "Description": "{{i18n:alesxmeads_orange_mead.description}}",
                    "Type": "ArtisanGoods",          
                    "Category": -26,
                    "Edibility": 20,
                    "Price": 100,
                    "ExcludeFromShippingCollection": "{{ShippingConfig}}",
                    "ContextTags":
                    ["wildflour_mead_item",
                    "alcohol_item",
                    "color_dark_brown"],

                    "Texture": "Mods/wildflour.alesxmeads/Objects",
                    "SpriteIndex": 91
            },
                "wildflour.alesxmeads_peach_mead": {
                    "Name": "wildflour.alesxmeads_peach_mead",
                    "DisplayName": "{{i18n:alesxmeads_peach_mead.name}}",
                    "Description": "{{i18n:alesxmeads_peach_mead.description}}",
                    "Type": "ArtisanGoods",          
                    "Category": -26,
                    "Edibility": 20,
                    "Price": 100,
                    "ExcludeFromShippingCollection": "{{ShippingConfig}}",
                    "ContextTags":
                    ["wildflour_mead_item",
                    "alcohol_item",
                    "color_dark_brown"],

                    "Texture": "Mods/wildflour.alesxmeads/Objects",
                    "SpriteIndex": 92
            },
                "wildflour.alesxmeads_spiced_mead": {
                    "Name": "wildflour.alesxmeads_spiced_mead",
                    "DisplayName": "{{i18n:alesxmeads_spiced_mead.name}}",
                    "Description": "{{i18n:alesxmeads_spiced_mead.description}}",
                    "Type": "ArtisanGoods",          
                    "Category": -26,
                    "Edibility": 20,
                    "Price": 100,
                    "ExcludeFromShippingCollection": "{{ShippingConfig}}",
                    "ContextTags":
                    ["wildflour_mead_item",
                    "alcohol_item",
                    "color_dark_brown"],

                    "Texture": "Mods/wildflour.alesxmeads/Objects",
                    "SpriteIndex": 93
            },
                "wildflour.alesxmeads_apricot_mead": {
                    "Name": "wildflour.alesxmeads_apricot_mead",
                    "DisplayName": "{{i18n:alesxmeads_apricot_mead.name}}",
                    "Description": "{{i18n:alesxmeads_apricot_mead.description}}",
                    "Type": "ArtisanGoods",          
                    "Category": -26,
                    "Edibility": 20,
                    "Price": 100,
                    "ExcludeFromShippingCollection": "{{ShippingConfig}}",
                    "ContextTags":
                    ["wildflour_mead_item",
                    "alcohol_item",
                    "color_dark_brown"],

                    "Texture": "Mods/wildflour.alesxmeads/Objects",
                    "SpriteIndex": 94
            },
                "wildflour.alesxmeads_starfruit_mead": {
                    "Name": "wildflour.alesxmeads_starfruit_mead",
                    "DisplayName": "{{i18n:alesxmeads_starfruit_mead.name}}",
                    "Description": "{{i18n:alesxmeads_starfruit_mead.description}}",
                    "Type": "ArtisanGoods",          
                    "Category": -26,
                    "Edibility": 20,
                    "Price": 100,
                    "ExcludeFromShippingCollection": "{{ShippingConfig}}",
                    "ContextTags":
                    ["wildflour_mead_item",
                    "alcohol_item",
                    "color_dark_brown"],

                    "Texture": "Mods/wildflour.alesxmeads/Objects",
                    "SpriteIndex": 95
            },
                "wildflour.alesxmeads_strawberry_mead": {
                    "Name": "wildflour.alesxmeads_strawberry_mead",
                    "DisplayName": "{{i18n:alesxmeads_strawberry_mead.name}}",
                    "Description": "{{i18n:alesxmeads_strawberry_mead.description}}",
                    "Type": "ArtisanGoods",          
                    "Category": -26,
                    "Edibility": 20,
                    "Price": 100,
                    "ExcludeFromShippingCollection": "{{ShippingConfig}}",
                    "ContextTags":
                    ["wildflour_mead_item",
                    "alcohol_item",
                    "color_dark_brown"],

                    "Texture": "Mods/wildflour.alesxmeads/Objects",
                    "SpriteIndex": 96
            },
                "wildflour.alesxmeads_melon_mead": {
                    "Name": "wildflour.alesxmeads_melon_mead",
                    "DisplayName": "{{i18n:alesxmeads_melon_mead.name}}",
                    "Description": "{{i18n:alesxmeads_melon_mead.description}}",
                    "Type": "ArtisanGoods",          
                    "Category": -26,
                    "Edibility": 20,
                    "Price": 100,
                    "ExcludeFromShippingCollection": "{{ShippingConfig}}",
                    "ContextTags":
                    ["wildflour_mead_item",
                    "alcohol_item",
                    "color_dark_brown"],

                    "Texture": "Mods/wildflour.alesxmeads/Objects",
                    "SpriteIndex": 97
            },
                "wildflour.alesxmeads_cherry_mead": {
                    "Name": "wildflour.alesxmeads_cherry_mead",
                    "DisplayName": "{{i18n:alesxmeads_cherry_mead.name}}",
                    "Description": "{{i18n:alesxmeads_cherry_mead.description}}",
                    "Type": "ArtisanGoods",          
                    "Category": -26,
                    "Edibility": 20,
                    "Price": 100,
                    "ExcludeFromShippingCollection": "{{ShippingConfig}}",
                    "ContextTags":
                    ["wildflour_mead_item",
                    "alcohol_item",
                    "color_dark_brown"],

                    "Texture": "Mods/wildflour.alesxmeads/Objects",
                    "SpriteIndex": 98
            },
                "wildflour.alesxmeads_pomegranate_mead": {
                    "Name": "wildflour.alesxmeads_pomegranate_mead",
                    "DisplayName": "{{i18n:alesxmeads_pomegranate_mead.name}}",
                    "Description": "{{i18n:alesxmeads_pomegranate_mead.description}}",
                    "Type": "ArtisanGoods",          
                    "Category": -26,
                    "Edibility": 20,
                    "Price": 100,
                    "ExcludeFromShippingCollection": "{{ShippingConfig}}",
                    "ContextTags":
                    ["wildflour_mead_item",
                    "alcohol_item",
                    "color_dark_brown"],

                    "Texture": "Mods/wildflour.alesxmeads/Objects",
                    "SpriteIndex": 99
            },
                "wildflour.alesxmeads_cranberry_mead": {
                    "Name": "wildflour.alesxmeads_cranberry_mead",
                    "DisplayName": "{{i18n:alesxmeads_cranberry_mead.name}}",
                    "Description": "{{i18n:alesxmeads_cranberry_mead.description}}",
                    "Type": "ArtisanGoods",          
                    "Category": -26,
                    "Edibility": 20,
                    "Price": 100,
                    "ExcludeFromShippingCollection": "{{ShippingConfig}}",
                    "ContextTags":
                    ["wildflour_mead_item",
                    "alcohol_item",
                    "color_dark_brown"],

                    "Texture": "Mods/wildflour.alesxmeads/Objects",
                    "SpriteIndex": 100
            },
                "wildflour.alesxmeads_coconut_mead": {
                    "Name": "wildflour.alesxmeads_coconut_mead",
                    "DisplayName": "{{i18n:alesxmeads_coconut_mead.name}}",
                    "Description": "{{i18n:alesxmeads_coconut_mead.description}}",
                    "Type": "ArtisanGoods",          
                    "Category": -26,
                    "Edibility": 20,
                    "Price": 100,
                    "ExcludeFromShippingCollection": "{{ShippingConfig}}",
                    "ContextTags":
                    ["wildflour_mead_item",
                    "alcohol_item",
                    "color_dark_brown"],

                    "Texture": "Mods/wildflour.alesxmeads/Objects",
                    "SpriteIndex": 101
            },
                "wildflour.alesxmeads_salmonberry_mead": {
                    "Name": "wildflour.alesxmeads_salmonberry_mead",
                    "DisplayName": "{{i18n:alesxmeads_salmonberry_mead.name}}",
                    "Description": "{{i18n:alesxmeads_salmonberry_mead.description}}",
                    "Type": "ArtisanGoods",          
                    "Category": -26,
                    "Edibility": 20,
                    "Price": 100,
                    "ExcludeFromShippingCollection": "{{ShippingConfig}}",
                    "ContextTags":
                    ["wildflour_mead_item",
                    "alcohol_item",
                    "color_dark_brown"],

                    "Texture": "Mods/wildflour.alesxmeads/Objects",
                    "SpriteIndex": 102
            }

            }
        },

    ]
}